{
  "name": "Kira",
  "slug": "kira",
  "gameVersion": "1.11.2",
  "versionId": "132",
  "scrapedAt": "2026-02-08T08:21:03.705Z",
  "activeRoles": [
    "offlane",
    "midlane",
    "carry"
  ],
  "roles": {
    "offlane": {
      "buildTabs": [
        {
          "name": "On-Hit/Crit",
          "items": [
            "Scattershot",
            "Vanquisher",
            "Ashbringer"
          ],
          "winRate": "33.3%",
          "matches": "12 Matches"
        },
        {
          "name": "On-Hit/Crit",
          "items": [
            "Scattershot",
            "Vanquisher",
            "Tainted Rounds"
          ],
          "winRate": "33.3%",
          "matches": "3 Matches"
        },
        {
          "name": "On-Hit/Crit",
          "items": [
            "Lightning Hawk",
            "Vanquisher",
            "Tainted Rounds"
          ],
          "winRate": "0.0%",
          "matches": "3 Matches"
        }
      ],
      "augments": [
        {
          "name": "Dusk's Embrace",
          "winRate": "33.33%",
          "matches": 6
        },
        {
          "name": "Bringer Of Mercy",
          "winRate": "20.00%",
          "matches": 5
        },
        {
          "name": "Siphoning Purge",
          "winRate": "100.00%",
          "matches": 1
        }
      ],
      "crests": [
        {
          "name": "Pacifier",
          "winRate": "30.00%",
          "matches": 10
        },
        {
          "name": "Eviscerator",
          "winRate": "50.00%",
          "matches": 2
        }
      ],
      "coreItems": {
        "items": [
          "Scattershot",
          "Vanquisher",
          "Ashbringer"
        ],
        "winRate": "33.33%",
        "matches": "12"
      },
      "itemSlots": {
        "4th": [
          {
            "name": "Imperator",
            "winRate": "25.00%",
            "matches": 4
          },
          {
            "name": "Demolisher",
            "winRate": "100.00%",
            "matches": 2
          },
          {
            "name": "Tainted Rounds",
            "winRate": "0.00%",
            "matches": 2
          }
        ],
        "5th": [
          {
            "name": "Demolisher",
            "winRate": "0.00%",
            "matches": 2
          },
          {
            "name": "Imperator",
            "winRate": "50.00%",
            "matches": 2
          },
          {
            "name": "Terminus",
            "winRate": "0.00%",
            "matches": 1
          }
        ],
        "6th": [
          {
            "name": "Tainted Rounds",
            "winRate": "100.00%",
            "matches": 1
          }
        ]
      },
      "skillPriority": [
        "Dusk",
        "Mercy",
        "Shadow Glide"
      ],
      "skillOrder": [
        {
          "name": "Dusk",
          "levels": [
            2,
            5,
            8,
            10,
            12,
            13
          ]
        },
        {
          "name": "Shadow Glide",
          "levels": [
            3,
            14,
            15,
            17,
            18
          ]
        },
        {
          "name": "Purge",
          "levels": [
            6,
            11,
            16
          ]
        },
        {
          "name": "Mercy",
          "levels": [
            1,
            4,
            7,
            9
          ]
        }
      ],
      "items": [
        {
          "name": "Pacifier",
          "slot": "crest",
          "winRate": 38.24,
          "matches": 68,
          "avgTime": "15:07",
          "avgTimeSec": 907
        },
        {
          "name": "Eviscerator",
          "slot": "crest",
          "winRate": 33.33,
          "matches": 12,
          "avgTime": "15:48",
          "avgTimeSec": 948
        },
        {
          "name": "Liberator",
          "slot": "crest",
          "winRate": 40,
          "matches": 5,
          "avgTime": "14:19",
          "avgTimeSec": 859
        },
        {
          "name": "Marksman Crest",
          "slot": "crest",
          "winRate": 0,
          "matches": 3,
          "avgTime": "0:13",
          "avgTimeSec": 13
        },
        {
          "name": "Ortus",
          "slot": "crest",
          "winRate": 66.67,
          "matches": 3,
          "avgTime": "14:54",
          "avgTimeSec": 894
        },
        {
          "name": "Scattershot",
          "slot": null,
          "winRate": 30.61,
          "matches": 49,
          "avgTime": "10:19",
          "avgTimeSec": 619
        },
        {
          "name": "Lightning Hawk",
          "slot": null,
          "winRate": 37.5,
          "matches": 8,
          "avgTime": "9:25",
          "avgTimeSec": 565
        },
        {
          "name": "Vanquisher",
          "slot": null,
          "winRate": 66.67,
          "matches": 6,
          "avgTime": "10:24",
          "avgTimeSec": 624
        },
        {
          "name": "Storm Breaker",
          "slot": null,
          "winRate": 40,
          "matches": 5,
          "avgTime": "10:34",
          "avgTimeSec": 634
        },
        {
          "name": "Ashbringer",
          "slot": null,
          "winRate": 25,
          "matches": 4,
          "avgTime": "9:41",
          "avgTimeSec": 581
        },
        {
          "name": "Vanquisher",
          "slot": null,
          "winRate": 25.71,
          "matches": 35,
          "avgTime": "18:03",
          "avgTimeSec": 1083
        },
        {
          "name": "Tainted Rounds",
          "slot": null,
          "winRate": 71.43,
          "matches": 14,
          "avgTime": "17:22",
          "avgTimeSec": 1042
        },
        {
          "name": "Sky Splitter",
          "slot": null,
          "winRate": 42.86,
          "matches": 7,
          "avgTime": "17:49",
          "avgTimeSec": 1069
        },
        {
          "name": "Scattershot",
          "slot": null,
          "winRate": 20,
          "matches": 5,
          "avgTime": "17:20",
          "avgTimeSec": 1040
        },
        {
          "name": "The Perforator",
          "slot": null,
          "winRate": 33.33,
          "matches": 3,
          "avgTime": "19:27",
          "avgTimeSec": 1167
        },
        {
          "name": "Ashbringer",
          "slot": null,
          "winRate": 33.33,
          "matches": 12,
          "avgTime": "22:53",
          "avgTimeSec": 1373
        },
        {
          "name": "Vanquisher",
          "slot": null,
          "winRate": 70,
          "matches": 10,
          "avgTime": "22:20",
          "avgTimeSec": 1340
        },
        {
          "name": "Tainted Rounds",
          "slot": null,
          "winRate": 12.5,
          "matches": 8,
          "avgTime": "22:43",
          "avgTimeSec": 1363
        },
        {
          "name": "Imperator",
          "slot": null,
          "winRate": 28.57,
          "matches": 7,
          "avgTime": "25:30",
          "avgTimeSec": 1530
        },
        {
          "name": "Demolisher",
          "slot": null,
          "winRate": 16.67,
          "matches": 6,
          "avgTime": "21:59",
          "avgTimeSec": 1319
        },
        {
          "name": "Imperator",
          "slot": null,
          "winRate": 33.33,
          "matches": 9,
          "avgTime": "29:22",
          "avgTimeSec": 1762
        },
        {
          "name": "Tainted Rounds",
          "slot": null,
          "winRate": 50,
          "matches": 8,
          "avgTime": "28:26",
          "avgTimeSec": 1706
        },
        {
          "name": "Ashbringer",
          "slot": null,
          "winRate": 71.43,
          "matches": 7,
          "avgTime": "28:45",
          "avgTimeSec": 1725
        },
        {
          "name": "Demolisher",
          "slot": null,
          "winRate": 100,
          "matches": 4,
          "avgTime": "28:52",
          "avgTimeSec": 1732
        },
        {
          "name": "Sky Splitter",
          "slot": null,
          "winRate": 66.67,
          "matches": 3,
          "avgTime": "27:59",
          "avgTimeSec": 1679
        },
        {
          "name": "Demolisher",
          "slot": null,
          "winRate": 50,
          "matches": 6,
          "avgTime": "32:26",
          "avgTimeSec": 1946
        },
        {
          "name": "Imperator",
          "slot": null,
          "winRate": 60,
          "matches": 5,
          "avgTime": "35:19",
          "avgTimeSec": 2119
        },
        {
          "name": "Terminus",
          "slot": null,
          "winRate": 66.67,
          "matches": 3,
          "avgTime": "32:25",
          "avgTimeSec": 1945
        },
        {
          "name": "Tainted Rounds",
          "slot": null,
          "winRate": 50,
          "matches": 2,
          "avgTime": "33:17",
          "avgTimeSec": 1997
        },
        {
          "name": "Viper",
          "slot": null,
          "winRate": 50,
          "matches": 2,
          "avgTime": "36:09",
          "avgTimeSec": 2169
        },
        {
          "name": "Imperator",
          "slot": null,
          "winRate": 100,
          "matches": 2,
          "avgTime": "40:45",
          "avgTimeSec": 2445
        },
        {
          "name": "Lightning Hawk",
          "slot": null,
          "winRate": 100,
          "matches": 2,
          "avgTime": "39:37",
          "avgTimeSec": 2377
        },
        {
          "name": "Storm Breaker",
          "slot": null,
          "winRate": 0,
          "matches": 1,
          "avgTime": "37:43",
          "avgTimeSec": 2263
        },
        {
          "name": "Tainted Rounds",
          "slot": null,
          "winRate": 100,
          "matches": 1,
          "avgTime": "39:48",
          "avgTimeSec": 2388
        },
        {
          "name": "Ruination",
          "slot": null,
          "winRate": 0,
          "matches": 1,
          "avgTime": "36:47",
          "avgTimeSec": 2207
        }
      ],
      "counters": [
        {
          "hero": "Terra",
          "winRate": 100,
          "matches": 3
        },
        {
          "hero": "Serath",
          "winRate": 100,
          "matches": 1
        },
        {
          "hero": "Feng Mao",
          "winRate": 100,
          "matches": 1
        },
        {
          "hero": "Shinbi",
          "winRate": 83.3,
          "matches": 6
        },
        {
          "hero": "Greystone",
          "winRate": 77.8,
          "matches": 9
        },
        {
          "hero": "Grux",
          "winRate": 66.7,
          "matches": 9
        },
        {
          "hero": "Bayle",
          "winRate": 66.7,
          "matches": 3
        },
        {
          "hero": "Akeron",
          "winRate": 62.5,
          "matches": 8
        },
        {
          "hero": "Crunch",
          "winRate": 50,
          "matches": 2
        },
        {
          "hero": "Steel",
          "winRate": 50,
          "matches": 4
        },
        {
          "hero": "Countess",
          "winRate": 50,
          "matches": 2
        },
        {
          "hero": "Zarus",
          "winRate": 50,
          "matches": 2
        },
        {
          "hero": "Kwang",
          "winRate": 42.9,
          "matches": 7
        },
        {
          "hero": "Sevarog",
          "winRate": 33.3,
          "matches": 3
        },
        {
          "hero": "Aurora",
          "winRate": 33.3,
          "matches": 6
        }
      ]
    },
    "midlane": {
      "buildTabs": [
        {
          "name": "On-Hit/Crit",
          "items": [
            "Scattershot",
            "Vanquisher",
            "Tainted Rounds"
          ],
          "winRate": "45.5%",
          "matches": "11 Matches"
        },
        {
          "name": "On-Hit/Crit",
          "items": [
            "Scattershot",
            "Vanquisher",
            "Ashbringer"
          ],
          "winRate": "55.6%",
          "matches": "9 Matches"
        },
        {
          "name": "Crit/On-Hit",
          "items": [
            "Vanquisher",
            "Imperator",
            "Tainted Rounds"
          ],
          "winRate": "66.7%",
          "matches": "3 Matches"
        }
      ],
      "augments": [
        {
          "name": "Dusk's Embrace",
          "winRate": "42.86%",
          "matches": 7
        },
        {
          "name": "Bringer Of Mercy",
          "winRate": "66.67%",
          "matches": 3
        },
        {
          "name": "Siphoning Purge",
          "winRate": "0.00%",
          "matches": 1
        }
      ],
      "crests": [
        {
          "name": "Pacifier",
          "winRate": "50.00%",
          "matches": 10
        },
        {
          "name": "Liberator",
          "winRate": "0.00%",
          "matches": 1
        }
      ],
      "coreItems": {
        "items": [
          "Scattershot",
          "Vanquisher",
          "Tainted Rounds"
        ],
        "winRate": "45.45%",
        "matches": "11"
      },
      "itemSlots": {
        "4th": [
          {
            "name": "Terminus",
            "winRate": "50.00%",
            "matches": 6
          },
          {
            "name": "Ashbringer",
            "winRate": "100.00%",
            "matches": 1
          },
          {
            "name": "Demolisher",
            "winRate": "100.00%",
            "matches": 1
          }
        ],
        "5th": [
          {
            "name": "Sky Splitter",
            "winRate": "66.67%",
            "matches": 3
          },
          {
            "name": "Demolisher",
            "winRate": "100.00%",
            "matches": 1
          }
        ],
        "6th": [
          {
            "name": "Imperator",
            "winRate": "100.00%",
            "matches": 1
          }
        ]
      },
      "skillPriority": [
        "Dusk",
        "Mercy",
        "Shadow Glide"
      ],
      "skillOrder": [
        {
          "name": "Dusk",
          "levels": [
            1,
            4,
            5,
            7,
            9
          ]
        },
        {
          "name": "Shadow Glide",
          "levels": [
            2,
            14,
            15,
            17,
            18
          ]
        },
        {
          "name": "Purge",
          "levels": [
            6,
            11,
            16
          ]
        },
        {
          "name": "Mercy",
          "levels": [
            3,
            8,
            10,
            12,
            13
          ]
        }
      ],
      "items": [
        {
          "name": "Pacifier",
          "slot": "crest",
          "winRate": 53.33,
          "matches": 60,
          "avgTime": "16:08",
          "avgTimeSec": 968
        },
        {
          "name": "Liberator",
          "slot": "crest",
          "winRate": 43.75,
          "matches": 16,
          "avgTime": "15:14",
          "avgTimeSec": 914
        },
        {
          "name": "Marksman Crest",
          "slot": "crest",
          "winRate": 0,
          "matches": 5,
          "avgTime": "0:10",
          "avgTimeSec": 10
        },
        {
          "name": "Ortus",
          "slot": "crest",
          "winRate": 50,
          "matches": 4,
          "avgTime": "12:46",
          "avgTimeSec": 766
        },
        {
          "name": "Exodus",
          "slot": "crest",
          "winRate": 75,
          "matches": 4,
          "avgTime": "14:34",
          "avgTimeSec": 874
        },
        {
          "name": "Scattershot",
          "slot": null,
          "winRate": 43.48,
          "matches": 46,
          "avgTime": "9:47",
          "avgTimeSec": 587
        },
        {
          "name": "Vanquisher",
          "slot": null,
          "winRate": 56.25,
          "matches": 16,
          "avgTime": "9:52",
          "avgTimeSec": 592
        },
        {
          "name": "Sky Splitter",
          "slot": null,
          "winRate": 44.44,
          "matches": 9,
          "avgTime": "10:10",
          "avgTimeSec": 610
        },
        {
          "name": "Lightning Hawk",
          "slot": null,
          "winRate": 57.14,
          "matches": 7,
          "avgTime": "9:39",
          "avgTimeSec": 579
        },
        {
          "name": "Storm Breaker",
          "slot": null,
          "winRate": 50,
          "matches": 6,
          "avgTime": "8:54",
          "avgTimeSec": 534
        },
        {
          "name": "Vanquisher",
          "slot": null,
          "winRate": 48.65,
          "matches": 37,
          "avgTime": "16:01",
          "avgTimeSec": 961
        },
        {
          "name": "Sky Splitter",
          "slot": null,
          "winRate": 28.57,
          "matches": 7,
          "avgTime": "17:13",
          "avgTimeSec": 1033
        },
        {
          "name": "Necrosis",
          "slot": null,
          "winRate": 71.43,
          "matches": 7,
          "avgTime": "15:44",
          "avgTimeSec": 944
        },
        {
          "name": "Tainted Rounds",
          "slot": null,
          "winRate": 33.33,
          "matches": 6,
          "avgTime": "16:22",
          "avgTimeSec": 982
        },
        {
          "name": "Lightning Hawk",
          "slot": null,
          "winRate": 33.33,
          "matches": 6,
          "avgTime": "17:24",
          "avgTimeSec": 1044
        },
        {
          "name": "Tainted Rounds",
          "slot": null,
          "winRate": 50,
          "matches": 18,
          "avgTime": "21:11",
          "avgTimeSec": 1271
        },
        {
          "name": "Ashbringer",
          "slot": null,
          "winRate": 73.33,
          "matches": 15,
          "avgTime": "22:38",
          "avgTimeSec": 1358
        },
        {
          "name": "Demolisher",
          "slot": null,
          "winRate": 25,
          "matches": 8,
          "avgTime": "24:08",
          "avgTimeSec": 1448
        },
        {
          "name": "Imperator",
          "slot": null,
          "winRate": 42.86,
          "matches": 7,
          "avgTime": "22:44",
          "avgTimeSec": 1364
        },
        {
          "name": "Vanquisher",
          "slot": null,
          "winRate": 42.86,
          "matches": 7,
          "avgTime": "22:01",
          "avgTimeSec": 1321
        },
        {
          "name": "Imperator",
          "slot": null,
          "winRate": 63.64,
          "matches": 11,
          "avgTime": "29:01",
          "avgTimeSec": 1741
        },
        {
          "name": "Terminus",
          "slot": null,
          "winRate": 70,
          "matches": 10,
          "avgTime": "25:13",
          "avgTimeSec": 1513
        },
        {
          "name": "Ashbringer",
          "slot": null,
          "winRate": 71.43,
          "matches": 7,
          "avgTime": "27:02",
          "avgTimeSec": 1622
        },
        {
          "name": "Demolisher",
          "slot": null,
          "winRate": 66.67,
          "matches": 6,
          "avgTime": "25:43",
          "avgTimeSec": 1543
        },
        {
          "name": "Tainted Rounds",
          "slot": null,
          "winRate": 50,
          "matches": 6,
          "avgTime": "28:17",
          "avgTimeSec": 1697
        },
        {
          "name": "Demolisher",
          "slot": null,
          "winRate": 72.73,
          "matches": 11,
          "avgTime": "32:26",
          "avgTimeSec": 1946
        },
        {
          "name": "Sky Splitter",
          "slot": null,
          "winRate": 75,
          "matches": 4,
          "avgTime": "25:33",
          "avgTimeSec": 1533
        },
        {
          "name": "Nuclear Rounds",
          "slot": null,
          "winRate": 50,
          "matches": 2,
          "avgTime": "33:36",
          "avgTimeSec": 2016
        },
        {
          "name": "Necrosis",
          "slot": null,
          "winRate": 100,
          "matches": 2,
          "avgTime": "33:49",
          "avgTimeSec": 2029
        },
        {
          "name": "Ashbringer",
          "slot": null,
          "winRate": 50,
          "matches": 2,
          "avgTime": "31:47",
          "avgTimeSec": 1907
        },
        {
          "name": "Nuclear Rounds",
          "slot": null,
          "winRate": 33.33,
          "matches": 3,
          "avgTime": "35:51",
          "avgTimeSec": 2151
        },
        {
          "name": "Lightning Hawk",
          "slot": null,
          "winRate": 100,
          "matches": 2,
          "avgTime": "34:44",
          "avgTimeSec": 2084
        },
        {
          "name": "Necrosis",
          "slot": null,
          "winRate": 0,
          "matches": 1,
          "avgTime": "38:24",
          "avgTimeSec": 2304
        },
        {
          "name": "Spectra",
          "slot": null,
          "winRate": 100,
          "matches": 1,
          "avgTime": "41:05",
          "avgTimeSec": 2465
        },
        {
          "name": "Ashbringer",
          "slot": null,
          "winRate": 100,
          "matches": 1,
          "avgTime": "35:07",
          "avgTimeSec": 2107
        }
      ],
      "counters": [
        {
          "hero": "The Fey",
          "winRate": 72.7,
          "matches": 11
        },
        {
          "hero": "Argus",
          "winRate": 69.2,
          "matches": 13
        },
        {
          "hero": "Renna",
          "winRate": 66.7,
          "matches": 3
        },
        {
          "hero": "Howitzer",
          "winRate": 60,
          "matches": 10
        },
        {
          "hero": "Countess",
          "winRate": 50,
          "matches": 2
        },
        {
          "hero": "Iggy & Scorch",
          "winRate": 50,
          "matches": 8
        },
        {
          "hero": "Wraith",
          "winRate": 44.4,
          "matches": 9
        },
        {
          "hero": "Lt. Belica",
          "winRate": 44.4,
          "matches": 9
        },
        {
          "hero": "Gadget",
          "winRate": 42.9,
          "matches": 7
        },
        {
          "hero": "Gideon",
          "winRate": 33.3,
          "matches": 9
        },
        {
          "hero": "Morigesh",
          "winRate": 25,
          "matches": 8
        }
      ]
    },
    "carry": {
      "buildTabs": [
        {
          "name": "On-Hit/Crit",
          "items": [
            "Scattershot",
            "Vanquisher",
            "Tainted Rounds"
          ],
          "winRate": "57.2%",
          "matches": "519 Matches"
        },
        {
          "name": "On-Hit/Crit",
          "items": [
            "Scattershot",
            "Vanquisher",
            "Ashbringer"
          ],
          "winRate": "56.1%",
          "matches": "547 Matches"
        },
        {
          "name": "Crit/On-Hit",
          "items": [
            "Scattershot",
            "Vanquisher",
            "Imperator"
          ],
          "winRate": "54.0%",
          "matches": "189 Matches"
        }
      ],
      "augments": [
        {
          "name": "Dusk's Embrace",
          "winRate": "56.55%",
          "matches": 313
        },
        {
          "name": "Siphoning Purge",
          "winRate": "58.82%",
          "matches": 119
        },
        {
          "name": "Bringer Of Mercy",
          "winRate": "57.47%",
          "matches": 87
        }
      ],
      "crests": [
        {
          "name": "Pacifier",
          "winRate": "56.23%",
          "matches": 313
        },
        {
          "name": "Eviscerator",
          "winRate": "66.13%",
          "matches": 62
        },
        {
          "name": "Liberator",
          "winRate": "53.60%",
          "matches": 125
        }
      ],
      "coreItems": {
        "items": [
          "Scattershot",
          "Vanquisher",
          "Tainted Rounds"
        ],
        "winRate": "57.23%",
        "matches": "519"
      },
      "itemSlots": {
        "4th": [
          {
            "name": "Ashbringer",
            "winRate": "61.54%",
            "matches": 91
          },
          {
            "name": "Imperator",
            "winRate": "63.06%",
            "matches": 111
          },
          {
            "name": "Demolisher",
            "winRate": "57.41%",
            "matches": 54
          }
        ],
        "5th": [
          {
            "name": "Demolisher",
            "winRate": "76.47%",
            "matches": 51
          },
          {
            "name": "Imperator",
            "winRate": "66.67%",
            "matches": 36
          },
          {
            "name": "Terminus",
            "winRate": "70.00%",
            "matches": 30
          }
        ],
        "6th": [
          {
            "name": "Imperator",
            "winRate": "62.50%",
            "matches": 16
          },
          {
            "name": "Sky Splitter",
            "winRate": "50.00%",
            "matches": 12
          },
          {
            "name": "Demolisher",
            "winRate": "55.56%",
            "matches": 9
          }
        ]
      },
      "skillPriority": [
        "Dusk",
        "Mercy",
        "Shadow Glide"
      ],
      "skillOrder": [
        {
          "name": "Dusk",
          "levels": [
            2,
            8,
            10,
            12,
            13
          ]
        },
        {
          "name": "Shadow Glide",
          "levels": [
            3,
            14,
            15,
            17,
            18
          ]
        },
        {
          "name": "Purge",
          "levels": [
            6,
            11,
            16
          ]
        },
        {
          "name": "Mercy",
          "levels": [
            1,
            4,
            5,
            7,
            9
          ]
        }
      ],
      "items": [
        {
          "name": "Pacifier",
          "slot": "crest",
          "winRate": 52.42,
          "matches": 4273,
          "avgTime": "15:38",
          "avgTimeSec": 938
        },
        {
          "name": "Liberator",
          "slot": "crest",
          "winRate": 51.74,
          "matches": 1094,
          "avgTime": "15:08",
          "avgTimeSec": 908
        },
        {
          "name": "Eviscerator",
          "slot": "crest",
          "winRate": 54.68,
          "matches": 823,
          "avgTime": "16:33",
          "avgTimeSec": 993
        },
        {
          "name": "Marksman Crest",
          "slot": "crest",
          "winRate": 29.34,
          "matches": 392,
          "avgTime": "0:07",
          "avgTimeSec": 7
        },
        {
          "name": "Ortus",
          "slot": "crest",
          "winRate": 57.34,
          "matches": 143,
          "avgTime": "16:08",
          "avgTimeSec": 968
        },
        {
          "name": "Scattershot",
          "slot": null,
          "winRate": 51.35,
          "matches": 3589,
          "avgTime": "9:55",
          "avgTimeSec": 595
        },
        {
          "name": "Vanquisher",
          "slot": null,
          "winRate": 49.5,
          "matches": 1313,
          "avgTime": "9:52",
          "avgTimeSec": 592
        },
        {
          "name": "Lightning Hawk",
          "slot": null,
          "winRate": 55.71,
          "matches": 955,
          "avgTime": "9:26",
          "avgTimeSec": 566
        },
        {
          "name": "Ashbringer",
          "slot": null,
          "winRate": 47.02,
          "matches": 151,
          "avgTime": "9:37",
          "avgTimeSec": 577
        },
        {
          "name": "Necrosis",
          "slot": null,
          "winRate": 56.85,
          "matches": 146,
          "avgTime": "9:12",
          "avgTimeSec": 552
        },
        {
          "name": "Vanquisher",
          "slot": null,
          "winRate": 53.55,
          "matches": 2803,
          "avgTime": "16:29",
          "avgTimeSec": 989
        },
        {
          "name": "Scattershot",
          "slot": null,
          "winRate": 50.77,
          "matches": 776,
          "avgTime": "16:40",
          "avgTimeSec": 1000
        },
        {
          "name": "Tainted Rounds",
          "slot": null,
          "winRate": 49.19,
          "matches": 620,
          "avgTime": "16:26",
          "avgTimeSec": 986
        },
        {
          "name": "Ashbringer",
          "slot": null,
          "winRate": 51.65,
          "matches": 395,
          "avgTime": "16:28",
          "avgTimeSec": 988
        },
        {
          "name": "Solaris",
          "slot": null,
          "winRate": 55.48,
          "matches": 292,
          "avgTime": "16:41",
          "avgTimeSec": 1001
        },
        {
          "name": "Tainted Rounds",
          "slot": null,
          "winRate": 54.81,
          "matches": 1434,
          "avgTime": "22:09",
          "avgTimeSec": 1329
        },
        {
          "name": "Ashbringer",
          "slot": null,
          "winRate": 55.63,
          "matches": 915,
          "avgTime": "22:06",
          "avgTimeSec": 1326
        },
        {
          "name": "Imperator",
          "slot": null,
          "winRate": 57.85,
          "matches": 548,
          "avgTime": "22:25",
          "avgTimeSec": 1345
        },
        {
          "name": "Vanquisher",
          "slot": null,
          "winRate": 55.79,
          "matches": 518,
          "avgTime": "22:18",
          "avgTimeSec": 1338
        },
        {
          "name": "Terminus",
          "slot": null,
          "winRate": 52.79,
          "matches": 305,
          "avgTime": "22:28",
          "avgTimeSec": 1348
        },
        {
          "name": "Imperator",
          "slot": null,
          "winRate": 60.7,
          "matches": 804,
          "avgTime": "27:13",
          "avgTimeSec": 1633
        },
        {
          "name": "Ashbringer",
          "slot": null,
          "winRate": 58.13,
          "matches": 492,
          "avgTime": "27:13",
          "avgTimeSec": 1633
        },
        {
          "name": "Tainted Rounds",
          "slot": null,
          "winRate": 59.66,
          "matches": 466,
          "avgTime": "26:59",
          "avgTimeSec": 1619
        },
        {
          "name": "Demolisher",
          "slot": null,
          "winRate": 57.56,
          "matches": 443,
          "avgTime": "27:04",
          "avgTimeSec": 1624
        },
        {
          "name": "Terminus",
          "slot": null,
          "winRate": 66.3,
          "matches": 273,
          "avgTime": "26:54",
          "avgTimeSec": 1614
        },
        {
          "name": "Demolisher",
          "slot": null,
          "winRate": 61.99,
          "matches": 442,
          "avgTime": "31:43",
          "avgTimeSec": 1903
        },
        {
          "name": "Imperator",
          "slot": null,
          "winRate": 65.41,
          "matches": 344,
          "avgTime": "31:44",
          "avgTimeSec": 1904
        },
        {
          "name": "Terminus",
          "slot": null,
          "winRate": 66.5,
          "matches": 197,
          "avgTime": "31:17",
          "avgTimeSec": 1877
        },
        {
          "name": "Tainted Rounds",
          "slot": null,
          "winRate": 63.08,
          "matches": 130,
          "avgTime": "31:31",
          "avgTimeSec": 1891
        },
        {
          "name": "Ashbringer",
          "slot": null,
          "winRate": 64.52,
          "matches": 93,
          "avgTime": "31:31",
          "avgTimeSec": 1891
        },
        {
          "name": "Imperator",
          "slot": null,
          "winRate": 61.25,
          "matches": 160,
          "avgTime": "36:29",
          "avgTimeSec": 2189
        },
        {
          "name": "Sky Splitter",
          "slot": null,
          "winRate": 68.42,
          "matches": 76,
          "avgTime": "35:58",
          "avgTimeSec": 2158
        },
        {
          "name": "Demolisher",
          "slot": null,
          "winRate": 52.24,
          "matches": 67,
          "avgTime": "37:21",
          "avgTimeSec": 2241
        },
        {
          "name": "Terminus",
          "slot": null,
          "winRate": 56,
          "matches": 50,
          "avgTime": "34:36",
          "avgTimeSec": 2076
        },
        {
          "name": "Tainted Rounds",
          "slot": null,
          "winRate": 56.82,
          "matches": 44,
          "avgTime": "36:15",
          "avgTimeSec": 2175
        }
      ],
      "counters": [
        {
          "hero": "Eden",
          "winRate": 53.6,
          "matches": 192
        },
        {
          "hero": "TwinBlast",
          "winRate": 50.3,
          "matches": 1086
        },
        {
          "hero": "Drongo",
          "winRate": 49.9,
          "matches": 984
        },
        {
          "hero": "Sparrow",
          "winRate": 49,
          "matches": 1282
        },
        {
          "hero": "Murdock",
          "winRate": 48.6,
          "matches": 1069
        },
        {
          "hero": "Skylar",
          "winRate": 48.3,
          "matches": 744
        },
        {
          "hero": "Revenant",
          "winRate": 47,
          "matches": 738
        },
        {
          "hero": "GRIM.exe",
          "winRate": 46.6,
          "matches": 371
        },
        {
          "hero": "Wraith",
          "winRate": 40.4,
          "matches": 203
        }
      ]
    }
  }
}