{
  "name": "Zarus",
  "slug": "zarus",
  "scrapedAt": "2026-02-08T05:49:31.336Z",
  "activeRoles": [
    "offlane",
    "jungle"
  ],
  "roles": {
    "offlane": {
      "buildTabs": [
        {
          "name": "Sustain/On-Hit",
          "items": [
            "Vyzar Carapace",
            "Tainted Blade",
            "Earthshaker"
          ],
          "winRate": "54.6%",
          "matches": "141 Matches"
        },
        {
          "name": "Anti Tank/On-Hit",
          "items": [
            "Augmentation",
            "Mutilator",
            "Basilisk"
          ],
          "winRate": "44.6%",
          "matches": "65 Matches"
        },
        {
          "name": "On-Hit/Anti Tank",
          "items": [
            "Augmentation",
            "Mutilator",
            "Tainted Blade"
          ],
          "winRate": "40.0%",
          "matches": "15 Matches"
        }
      ],
      "augments": [
        {
          "name": "Master Of Spears",
          "winRate": "54.88%",
          "matches": "82"
        },
        {
          "name": "The Ascended",
          "winRate": "57.41%",
          "matches": "54"
        },
        {
          "name": "Flow State",
          "winRate": "20.00%",
          "matches": "5"
        }
      ],
      "crests": [
        {
          "name": "Judgement",
          "winRate": "56.15%",
          "matches": "130"
        },
        {
          "name": "Iceskorn Talons",
          "winRate": "33.33%",
          "matches": "9"
        },
        {
          "name": "Brutallax",
          "winRate": "100.00%",
          "matches": "1"
        }
      ],
      "coreItems": {
        "items": [
          "Vyzar Carapace",
          "Tainted Blade",
          "Earthshaker"
        ],
        "winRate": "54.61%",
        "matches": "141"
      },
      "itemSlots": {
        "4th": [
          {
            "name": "Salvation",
            "winRate": "66.20%",
            "matches": "71"
          },
          {
            "name": "Citadel",
            "winRate": "28.57%",
            "matches": "7"
          },
          {
            "name": "Aegis Of Agawar",
            "winRate": "75.00%",
            "matches": "8"
          }
        ],
        "5th": [
          {
            "name": "Aegis Of Agawar",
            "winRate": "58.33%",
            "matches": "24"
          },
          {
            "name": "Citadel",
            "winRate": "66.67%",
            "matches": "6"
          },
          {
            "name": "Salvation",
            "winRate": "33.33%",
            "matches": "3"
          }
        ],
        "6th": [
          {
            "name": "Citadel",
            "winRate": "80.00%",
            "matches": "5"
          },
          {
            "name": "Aegis Of Agawar",
            "winRate": "60.00%",
            "matches": "5"
          },
          {
            "name": "Mutilator",
            "winRate": "100.00%",
            "matches": "1"
          }
        ]
      },
      "skillPriority": [
        "Spear of Nyr",
        "Barricade",
        "Evade"
      ],
      "skillOrder": [
        {
          "name": "Barricade",
          "levels": [
            2,
            8,
            10,
            12,
            13
          ]
        },
        {
          "name": "Evade",
          "levels": [
            3,
            14,
            15,
            17,
            18
          ]
        },
        {
          "name": "Coliseum",
          "levels": [
            6,
            11,
            16
          ]
        },
        {
          "name": "Spear of Nyr",
          "levels": [
            1,
            4,
            5,
            7,
            9
          ]
        }
      ],
      "counters": [
        {
          "hero": "Akeron",
          "winRate": 60.5,
          "matches": 81
        },
        {
          "hero": "Grux",
          "winRate": 60.3,
          "matches": 136
        },
        {
          "hero": "Greystone",
          "winRate": 58.2,
          "matches": 239
        },
        {
          "hero": "Kwang",
          "winRate": 54.3,
          "matches": 92
        },
        {
          "hero": "Sevarog",
          "winRate": 54.2,
          "matches": 131
        },
        {
          "hero": "Shinbi",
          "winRate": 53.3,
          "matches": 137
        },
        {
          "hero": "Terra",
          "winRate": 51.1,
          "matches": 88
        },
        {
          "hero": "Bayle",
          "winRate": 50,
          "matches": 118
        },
        {
          "hero": "Feng Mao",
          "winRate": 50,
          "matches": 28
        },
        {
          "hero": "Aurora",
          "winRate": 49.6,
          "matches": 121
        },
        {
          "hero": "Countess",
          "winRate": 48.6,
          "matches": 70
        },
        {
          "hero": "Crunch",
          "winRate": 47.6,
          "matches": 82
        },
        {
          "hero": "Steel",
          "winRate": 42.2,
          "matches": 90
        },
        {
          "hero": "Serath",
          "winRate": 29.2,
          "matches": 24
        }
      ],
      "items": [
        {
          "name": "Judgement",
          "winRate": 47.31,
          "matches": 1357,
          "avgTime": "12:18"
        },
        {
          "name": "Iceskorn Talons",
          "winRate": 42.13,
          "matches": 216,
          "avgTime": "12:34"
        },
        {
          "name": "Brutallax",
          "winRate": 55.56,
          "matches": 63,
          "avgTime": "12:05"
        },
        {
          "name": "Saphir's Mantle",
          "winRate": 56.86,
          "matches": 51,
          "avgTime": "15:27"
        },
        {
          "name": "Ortus",
          "winRate": 39.39,
          "matches": 33,
          "avgTime": "14:55"
        },
        {
          "name": "Vyzar Carapace",
          "winRate": 48.21,
          "matches": 392,
          "avgTime": "10:01"
        },
        {
          "name": "Augmentation",
          "winRate": 41.73,
          "matches": 369,
          "avgTime": "10:43"
        },
        {
          "name": "Tainted Blade",
          "winRate": 46.51,
          "matches": 215,
          "avgTime": "9:55"
        },
        {
          "name": "Overlord",
          "winRate": 54.65,
          "matches": 172,
          "avgTime": "9:27"
        },
        {
          "name": "Mutilator",
          "winRate": 53.89,
          "matches": 167,
          "avgTime": "10:27"
        },
        {
          "name": "Tainted Blade",
          "winRate": 50.44,
          "matches": 454,
          "avgTime": "17:10"
        },
        {
          "name": "Mutilator",
          "winRate": 45.28,
          "matches": 254,
          "avgTime": "17:41"
        },
        {
          "name": "Augmentation",
          "winRate": 53.06,
          "matches": 196,
          "avgTime": "17:41"
        },
        {
          "name": "Vyzar Carapace",
          "winRate": 49.68,
          "matches": 155,
          "avgTime": "16:41"
        },
        {
          "name": "Earthshaker",
          "winRate": 50,
          "matches": 90,
          "avgTime": "17:25"
        },
        {
          "name": "Earthshaker",
          "winRate": 54.93,
          "matches": 213,
          "avgTime": "23:03"
        },
        {
          "name": "Tainted Blade",
          "winRate": 49.68,
          "matches": 157,
          "avgTime": "22:56"
        },
        {
          "name": "Basilisk",
          "winRate": 44.92,
          "matches": 118,
          "avgTime": "23:52"
        },
        {
          "name": "Mutilator",
          "winRate": 47.57,
          "matches": 103,
          "avgTime": "23:21"
        },
        {
          "name": "Augmentation",
          "winRate": 56,
          "matches": 100,
          "avgTime": "23:32"
        },
        {
          "name": "Salvation",
          "winRate": 58.76,
          "matches": 177,
          "avgTime": "28:28"
        },
        {
          "name": "Citadel",
          "winRate": 53.19,
          "matches": 94,
          "avgTime": "28:27"
        },
        {
          "name": "Aegis Of Agawar",
          "winRate": 62.79,
          "matches": 43,
          "avgTime": "28:10"
        },
        {
          "name": "Tainted Blade",
          "winRate": 52.5,
          "matches": 40,
          "avgTime": "29:05"
        },
        {
          "name": "Basilisk",
          "winRate": 55.88,
          "matches": 34,
          "avgTime": "27:22"
        },
        {
          "name": "Aegis Of Agawar",
          "winRate": 56.9,
          "matches": 58,
          "avgTime": "34:10"
        },
        {
          "name": "Citadel",
          "winRate": 58.54,
          "matches": 41,
          "avgTime": "33:48"
        },
        {
          "name": "Salvation",
          "winRate": 47.5,
          "matches": 40,
          "avgTime": "33:00"
        },
        {
          "name": "Solstice",
          "winRate": 56.25,
          "matches": 16,
          "avgTime": "32:51"
        },
        {
          "name": "Tainted Blade",
          "winRate": 46.15,
          "matches": 13,
          "avgTime": "33:16"
        },
        {
          "name": "Citadel",
          "winRate": 55.56,
          "matches": 18,
          "avgTime": "39:56"
        },
        {
          "name": "Aegis Of Agawar",
          "winRate": 60,
          "matches": 15,
          "avgTime": "37:04"
        },
        {
          "name": "Mistmeadow Buckler",
          "winRate": 55.56,
          "matches": 9,
          "avgTime": "38:25"
        },
        {
          "name": "Mutilator",
          "winRate": 71.43,
          "matches": 7,
          "avgTime": "33:43"
        },
        {
          "name": "Salvation",
          "winRate": 66.67,
          "matches": 6,
          "avgTime": "38:13"
        }
      ]
    },
    "jungle": {
      "buildTabs": [
        {
          "name": "Sustain/On-Hit",
          "items": [
            "Earthshaker",
            "Vyzar Carapace",
            "Tainted Blade"
          ],
          "winRate": "59.3%",
          "matches": "209 Matches"
        },
        {
          "name": "On-Hit/Anti Tank",
          "items": [
            "Berserker's Axe",
            "Augmentation",
            "Basilisk"
          ],
          "winRate": "49.6%",
          "matches": "137 Matches"
        },
        {
          "name": "On-Hit",
          "items": [
            "Berserker's Axe",
            "Augmentation",
            "Tainted Blade"
          ],
          "winRate": "49.3%",
          "matches": "73 Matches"
        }
      ],
      "augments": [
        {
          "name": "Flow State",
          "winRate": "56.52%",
          "matches": "115"
        },
        {
          "name": "The Ascended",
          "winRate": "65.82%",
          "matches": "79"
        },
        {
          "name": "Master Of Spears",
          "winRate": "46.67%",
          "matches": "15"
        }
      ],
      "crests": [
        {
          "name": "Judgement",
          "winRate": "58.67%",
          "matches": "196"
        },
        {
          "name": "Saphir's Mantle",
          "winRate": "100.00%",
          "matches": "1"
        },
        {
          "name": "Iceskorn Talons",
          "winRate": "66.67%",
          "matches": "6"
        }
      ],
      "coreItems": {
        "items": [
          "Earthshaker",
          "Vyzar Carapace",
          "Tainted Blade"
        ],
        "winRate": "59.33%",
        "matches": "209"
      },
      "itemSlots": {
        "4th": [
          {
            "name": "Salvation",
            "winRate": "65.52%",
            "matches": "116"
          },
          {
            "name": "Citadel",
            "winRate": "75.00%",
            "matches": "4"
          },
          {
            "name": "Aegis Of Agawar",
            "winRate": "75.00%",
            "matches": "4"
          }
        ],
        "5th": [
          {
            "name": "Citadel",
            "winRate": "62.16%",
            "matches": "37"
          },
          {
            "name": "Aegis Of Agawar",
            "winRate": "75.00%",
            "matches": "4"
          },
          {
            "name": "Salvation",
            "winRate": "75.00%",
            "matches": "4"
          }
        ],
        "6th": [
          {
            "name": "Aegis Of Agawar",
            "winRate": "61.54%",
            "matches": "13"
          },
          {
            "name": "Citadel",
            "winRate": "100.00%",
            "matches": "2"
          },
          {
            "name": "Unbroken Will",
            "winRate": "100.00%",
            "matches": "1"
          }
        ]
      },
      "skillPriority": [
        "Spear of Nyr",
        "Barricade",
        "Evade"
      ],
      "skillOrder": [
        {
          "name": "Barricade",
          "levels": [
            2,
            8,
            10,
            12,
            13
          ]
        },
        {
          "name": "Evade",
          "levels": [
            3,
            14,
            15,
            17,
            18
          ]
        },
        {
          "name": "Coliseum",
          "levels": [
            6,
            11,
            16
          ]
        },
        {
          "name": "Spear of Nyr",
          "levels": [
            1,
            4,
            5,
            7,
            9
          ]
        }
      ],
      "counters": [
        {
          "hero": "Wukong",
          "winRate": 59.3,
          "matches": 59
        },
        {
          "hero": "Rampage",
          "winRate": 55.6,
          "matches": 302
        },
        {
          "hero": "Aurora",
          "winRate": 53.2,
          "matches": 139
        },
        {
          "hero": "Akeron",
          "winRate": 52.2,
          "matches": 113
        },
        {
          "hero": "Serath",
          "winRate": 51.6,
          "matches": 225
        },
        {
          "hero": "Khaimera",
          "winRate": 51.4,
          "matches": 401
        },
        {
          "hero": "Riktor",
          "winRate": 51.2,
          "matches": 84
        },
        {
          "hero": "Grux",
          "winRate": 50.9,
          "matches": 116
        },
        {
          "hero": "Crunch",
          "winRate": 49.5,
          "matches": 198
        },
        {
          "hero": "Boris",
          "winRate": 48,
          "matches": 373
        },
        {
          "hero": "Kwang",
          "winRate": 46.9,
          "matches": 113
        },
        {
          "hero": "Greystone",
          "winRate": 46.5,
          "matches": 127
        },
        {
          "hero": "Terra",
          "winRate": 45.9,
          "matches": 37
        },
        {
          "hero": "Yin",
          "winRate": 45.3,
          "matches": 106
        },
        {
          "hero": "Shinbi",
          "winRate": 44.8,
          "matches": 58
        },
        {
          "hero": "Bayle",
          "winRate": 44.8,
          "matches": 96
        },
        {
          "hero": "Sevarog",
          "winRate": 43.3,
          "matches": 134
        },
        {
          "hero": "Feng Mao",
          "winRate": 43.1,
          "matches": 160
        },
        {
          "hero": "Kallari",
          "winRate": 42.4,
          "matches": 99
        },
        {
          "hero": "Yurei",
          "winRate": 41.2,
          "matches": 136
        },
        {
          "hero": "Countess",
          "winRate": 36.4,
          "matches": 88
        }
      ],
      "items": [
        {
          "name": "Judgement",
          "winRate": 51.99,
          "matches": 2135,
          "avgTime": "11:48"
        },
        {
          "name": "Iceskorn Talons",
          "winRate": 52.56,
          "matches": 371,
          "avgTime": "11:45"
        },
        {
          "name": "Ortus",
          "winRate": 51.63,
          "matches": 184,
          "avgTime": "12:46"
        },
        {
          "name": "Brutallax",
          "winRate": 52.67,
          "matches": 150,
          "avgTime": "11:30"
        },
        {
          "name": "Saphir's Mantle",
          "winRate": 49.59,
          "matches": 121,
          "avgTime": "12:05"
        },
        {
          "name": "Berserker's Axe",
          "winRate": 50.88,
          "matches": 796,
          "avgTime": "9:03"
        },
        {
          "name": "Manta Scythe",
          "winRate": 51.25,
          "matches": 638,
          "avgTime": "8:22"
        },
        {
          "name": "Earthshaker",
          "winRate": 55.06,
          "matches": 425,
          "avgTime": "9:06"
        },
        {
          "name": "Overlord",
          "winRate": 53.56,
          "matches": 351,
          "avgTime": "8:29"
        },
        {
          "name": "Augmentation",
          "winRate": 52.06,
          "matches": 315,
          "avgTime": "9:32"
        },
        {
          "name": "Tainted Blade",
          "winRate": 52.22,
          "matches": 676,
          "avgTime": "15:28"
        },
        {
          "name": "Augmentation",
          "winRate": 51.63,
          "matches": 645,
          "avgTime": "16:11"
        },
        {
          "name": "Vyzar Carapace",
          "winRate": 54.16,
          "matches": 445,
          "avgTime": "15:55"
        },
        {
          "name": "Berserker's Axe",
          "winRate": 54.02,
          "matches": 361,
          "avgTime": "15:48"
        },
        {
          "name": "Mutilator",
          "winRate": 55.05,
          "matches": 109,
          "avgTime": "15:57"
        },
        {
          "name": "Tainted Blade",
          "winRate": 56.79,
          "matches": 486,
          "avgTime": "21:49"
        },
        {
          "name": "Augmentation",
          "winRate": 53.67,
          "matches": 313,
          "avgTime": "22:12"
        },
        {
          "name": "Basilisk",
          "winRate": 46.75,
          "matches": 231,
          "avgTime": "22:37"
        },
        {
          "name": "Gaia Greaves",
          "winRate": 60.31,
          "matches": 194,
          "avgTime": "20:42"
        },
        {
          "name": "Vyzar Carapace",
          "winRate": 50.57,
          "matches": 176,
          "avgTime": "21:19"
        },
        {
          "name": "Salvation",
          "winRate": 62.61,
          "matches": 345,
          "avgTime": "27:29"
        },
        {
          "name": "Citadel",
          "winRate": 54.68,
          "matches": 139,
          "avgTime": "27:06"
        },
        {
          "name": "Aegis Of Agawar",
          "winRate": 57.81,
          "matches": 128,
          "avgTime": "27:21"
        },
        {
          "name": "Solstice",
          "winRate": 67.29,
          "matches": 107,
          "avgTime": "26:55"
        },
        {
          "name": "Gaia Greaves",
          "winRate": 63,
          "matches": 100,
          "avgTime": "25:52"
        },
        {
          "name": "Citadel",
          "winRate": 58.52,
          "matches": 135,
          "avgTime": "32:43"
        },
        {
          "name": "Salvation",
          "winRate": 67.47,
          "matches": 83,
          "avgTime": "31:18"
        },
        {
          "name": "Aegis Of Agawar",
          "winRate": 60.66,
          "matches": 61,
          "avgTime": "32:01"
        },
        {
          "name": "Solstice",
          "winRate": 60.53,
          "matches": 38,
          "avgTime": "33:07"
        },
        {
          "name": "Rapture",
          "winRate": 64.71,
          "matches": 34,
          "avgTime": "32:39"
        },
        {
          "name": "Aegis Of Agawar",
          "winRate": 67.44,
          "matches": 43,
          "avgTime": "36:58"
        },
        {
          "name": "Citadel",
          "winRate": 77.42,
          "matches": 31,
          "avgTime": "37:58"
        },
        {
          "name": "Salvation",
          "winRate": 71.43,
          "matches": 21,
          "avgTime": "36:04"
        },
        {
          "name": "Gaia Greaves",
          "winRate": 62.5,
          "matches": 16,
          "avgTime": "37:14"
        },
        {
          "name": "Solstice",
          "winRate": 50,
          "matches": 12,
          "avgTime": "37:23"
        }
      ]
    }
  }
}