{
 "meta": {
  "source": "omeda.city matches.json (official Omeda public API), ranked rows only",
  "generatedAt": "2026-07-12T03:26:06.137Z",
  "windowHours": 36,
  "pages": 120,
  "matches": 4692,
  "tiers": {
   "bronze": {
    "playerRows": 13073
   },
   "silver": {
    "playerRows": 17461
   },
   "gold": {
    "playerRows": 11446
   },
   "platinum": {
    "playerRows": 4520
   },
   "diamond+": {
    "playerRows": 420
   }
  },
  "note": "per PLAYER ROW by that player’s own rank code (tens digit = tier; 5+ pooled as diamond+); a mixed-tier match feeds each player’s own tier; rows with no rank dropped. Coarser buckets (e.g. Plat+) derive by summing tiers."
 },
 "heroes": {
  "adele": {
   "tiers": {
    "bronze": {
     "n": 247,
     "w": 126
    },
    "gold": {
     "n": 208,
     "w": 93
    },
    "silver": {
     "n": 281,
     "w": 129
    },
    "platinum": {
     "n": 78,
     "w": 42
    },
    "diamond+": {
     "n": 9,
     "w": 4
    }
   },
   "byRole": {
    "support": {
     "bronze": {
      "n": 140,
      "w": 79
     },
     "gold": {
      "n": 142,
      "w": 65
     },
     "silver": {
      "n": 173,
      "w": 84
     },
     "platinum": {
      "n": 66,
      "w": 37
     },
     "diamond+": {
      "n": 7,
      "w": 3
     }
    },
    "offlane": {
     "gold": {
      "n": 59,
      "w": 26
     },
     "platinum": {
      "n": 12,
      "w": 5
     },
     "bronze": {
      "n": 90,
      "w": 40
     },
     "silver": {
      "n": 93,
      "w": 43
     },
     "diamond+": {
      "n": 2,
      "w": 1
     }
    },
    "jungle": {
     "bronze": {
      "n": 15,
      "w": 7
     },
     "silver": {
      "n": 14,
      "w": 2
     },
     "gold": {
      "n": 7,
      "w": 2
     }
    },
    "midlane": {
     "silver": {
      "n": 1,
      "w": 0
     },
     "bronze": {
      "n": 1,
      "w": 0
     }
    },
    "carry": {
     "bronze": {
      "n": 1,
      "w": 0
     }
    }
   }
  },
  "akeron": {
   "tiers": {
    "bronze": {
     "n": 135,
     "w": 68
    },
    "silver": {
     "n": 133,
     "w": 58
    },
    "platinum": {
     "n": 75,
     "w": 40
    },
    "gold": {
     "n": 120,
     "w": 51
    },
    "diamond+": {
     "n": 4,
     "w": 4
    }
   },
   "byRole": {
    "jungle": {
     "bronze": {
      "n": 30,
      "w": 9
     },
     "silver": {
      "n": 29,
      "w": 13
     },
     "gold": {
      "n": 24,
      "w": 9
     },
     "platinum": {
      "n": 17,
      "w": 8
     },
     "diamond+": {
      "n": 2,
      "w": 2
     }
    },
    "offlane": {
     "silver": {
      "n": 94,
      "w": 40
     },
     "bronze": {
      "n": 92,
      "w": 52
     },
     "gold": {
      "n": 89,
      "w": 40
     },
     "platinum": {
      "n": 47,
      "w": 29
     },
     "diamond+": {
      "n": 1,
      "w": 1
     }
    },
    "midlane": {
     "platinum": {
      "n": 7,
      "w": 1
     },
     "bronze": {
      "n": 4,
      "w": 0
     },
     "gold": {
      "n": 2,
      "w": 0
     },
     "silver": {
      "n": 5,
      "w": 3
     }
    },
    "support": {
     "gold": {
      "n": 5,
      "w": 2
     },
     "bronze": {
      "n": 9,
      "w": 7
     },
     "platinum": {
      "n": 4,
      "w": 2
     },
     "silver": {
      "n": 5,
      "w": 2
     },
     "diamond+": {
      "n": 1,
      "w": 1
     }
    }
   }
  },
  "argus": {
   "tiers": {
    "silver": {
     "n": 444,
     "w": 220
    },
    "bronze": {
     "n": 444,
     "w": 231
    },
    "platinum": {
     "n": 127,
     "w": 65
    },
    "gold": {
     "n": 276,
     "w": 138
    },
    "diamond+": {
     "n": 5,
     "w": 3
    }
   },
   "byRole": {
    "midlane": {
     "silver": {
      "n": 292,
      "w": 148
     },
     "bronze": {
      "n": 257,
      "w": 152
     },
     "platinum": {
      "n": 114,
      "w": 60
     },
     "gold": {
      "n": 213,
      "w": 109
     },
     "diamond+": {
      "n": 4,
      "w": 3
     }
    },
    "support": {
     "silver": {
      "n": 130,
      "w": 62
     },
     "bronze": {
      "n": 179,
      "w": 77
     },
     "gold": {
      "n": 59,
      "w": 27
     },
     "platinum": {
      "n": 12,
      "w": 5
     },
     "diamond+": {
      "n": 1,
      "w": 0
     }
    },
    "offlane": {
     "silver": {
      "n": 12,
      "w": 8
     },
     "bronze": {
      "n": 6,
      "w": 2
     },
     "gold": {
      "n": 2,
      "w": 1
     },
     "platinum": {
      "n": 1,
      "w": 0
     }
    },
    "carry": {
     "bronze": {
      "n": 1,
      "w": 0
     },
     "gold": {
      "n": 1,
      "w": 1
     },
     "silver": {
      "n": 8,
      "w": 2
     }
    },
    "jungle": {
     "bronze": {
      "n": 1,
      "w": 0
     },
     "silver": {
      "n": 2,
      "w": 0
     },
     "gold": {
      "n": 1,
      "w": 0
     }
    }
   }
  },
  "aurora": {
   "tiers": {
    "platinum": {
     "n": 75,
     "w": 40
    },
    "silver": {
     "n": 395,
     "w": 208
    },
    "bronze": {
     "n": 310,
     "w": 173
    },
    "gold": {
     "n": 265,
     "w": 144
    },
    "diamond+": {
     "n": 4,
     "w": 2
    }
   },
   "byRole": {
    "jungle": {
     "platinum": {
      "n": 37,
      "w": 21
     },
     "silver": {
      "n": 174,
      "w": 88
     },
     "gold": {
      "n": 100,
      "w": 58
     },
     "bronze": {
      "n": 140,
      "w": 78
     },
     "diamond+": {
      "n": 1,
      "w": 0
     }
    },
    "offlane": {
     "platinum": {
      "n": 26,
      "w": 11
     },
     "bronze": {
      "n": 133,
      "w": 68
     },
     "silver": {
      "n": 154,
      "w": 81
     },
     "gold": {
      "n": 109,
      "w": 55
     },
     "diamond+": {
      "n": 1,
      "w": 0
     }
    },
    "support": {
     "platinum": {
      "n": 11,
      "w": 7
     },
     "gold": {
      "n": 54,
      "w": 30
     },
     "bronze": {
      "n": 31,
      "w": 23
     },
     "silver": {
      "n": 58,
      "w": 33
     },
     "diamond+": {
      "n": 2,
      "w": 2
     }
    },
    "midlane": {
     "bronze": {
      "n": 6,
      "w": 4
     },
     "silver": {
      "n": 8,
      "w": 6
     },
     "gold": {
      "n": 2,
      "w": 1
     },
     "platinum": {
      "n": 1,
      "w": 1
     }
    },
    "carry": {
     "silver": {
      "n": 1,
      "w": 0
     }
    }
   }
  },
  "bayle": {
   "tiers": {
    "silver": {
     "n": 540,
     "w": 273
    },
    "platinum": {
     "n": 97,
     "w": 44
    },
    "bronze": {
     "n": 456,
     "w": 238
    },
    "gold": {
     "n": 331,
     "w": 161
    },
    "diamond+": {
     "n": 9,
     "w": 2
    }
   },
   "byRole": {
    "support": {
     "silver": {
      "n": 13,
      "w": 7
     },
     "platinum": {
      "n": 3,
      "w": 1
     },
     "bronze": {
      "n": 6,
      "w": 3
     },
     "gold": {
      "n": 12,
      "w": 6
     }
    },
    "offlane": {
     "silver": {
      "n": 377,
      "w": 203
     },
     "bronze": {
      "n": 323,
      "w": 175
     },
     "gold": {
      "n": 217,
      "w": 102
     },
     "platinum": {
      "n": 74,
      "w": 32
     },
     "diamond+": {
      "n": 8,
      "w": 2
     }
    },
    "jungle": {
     "platinum": {
      "n": 20,
      "w": 11
     },
     "silver": {
      "n": 145,
      "w": 63
     },
     "bronze": {
      "n": 126,
      "w": 60
     },
     "gold": {
      "n": 101,
      "w": 53
     },
     "diamond+": {
      "n": 1,
      "w": 0
     }
    },
    "midlane": {
     "bronze": {
      "n": 1,
      "w": 0
     },
     "gold": {
      "n": 1,
      "w": 0
     },
     "silver": {
      "n": 4,
      "w": 0
     }
    },
    "carry": {
     "silver": {
      "n": 1,
      "w": 0
     }
    }
   }
  },
  "boris": {
   "tiers": {
    "gold": {
     "n": 192,
     "w": 105
    },
    "bronze": {
     "n": 227,
     "w": 121
    },
    "silver": {
     "n": 276,
     "w": 145
    },
    "platinum": {
     "n": 67,
     "w": 41
    },
    "diamond+": {
     "n": 4,
     "w": 2
    }
   },
   "byRole": {
    "jungle": {
     "gold": {
      "n": 189,
      "w": 105
     },
     "bronze": {
      "n": 225,
      "w": 120
     },
     "silver": {
      "n": 268,
      "w": 144
     },
     "platinum": {
      "n": 67,
      "w": 41
     },
     "diamond+": {
      "n": 3,
      "w": 2
     }
    },
    "offlane": {
     "bronze": {
      "n": 2,
      "w": 1
     },
     "diamond+": {
      "n": 1,
      "w": 0
     },
     "silver": {
      "n": 6,
      "w": 0
     },
     "gold": {
      "n": 3,
      "w": 0
     }
    },
    "support": {
     "silver": {
      "n": 1,
      "w": 1
     }
    },
    "midlane": {
     "silver": {
      "n": 1,
      "w": 0
     }
    }
   }
  },
  "countess": {
   "tiers": {
    "silver": {
     "n": 304,
     "w": 144
    },
    "gold": {
     "n": 204,
     "w": 95
    },
    "bronze": {
     "n": 208,
     "w": 90
    },
    "platinum": {
     "n": 82,
     "w": 47
    },
    "diamond+": {
     "n": 6,
     "w": 4
    }
   },
   "byRole": {
    "offlane": {
     "silver": {
      "n": 86,
      "w": 36
     },
     "gold": {
      "n": 59,
      "w": 33
     },
     "bronze": {
      "n": 54,
      "w": 22
     },
     "platinum": {
      "n": 21,
      "w": 15
     },
     "diamond+": {
      "n": 5,
      "w": 4
     }
    },
    "midlane": {
     "gold": {
      "n": 96,
      "w": 48
     },
     "silver": {
      "n": 128,
      "w": 64
     },
     "platinum": {
      "n": 40,
      "w": 21
     },
     "bronze": {
      "n": 95,
      "w": 44
     }
    },
    "jungle": {
     "silver": {
      "n": 82,
      "w": 41
     },
     "bronze": {
      "n": 55,
      "w": 23
     },
     "gold": {
      "n": 47,
      "w": 13
     },
     "diamond+": {
      "n": 1,
      "w": 0
     },
     "platinum": {
      "n": 18,
      "w": 9
     }
    },
    "support": {
     "silver": {
      "n": 8,
      "w": 3
     },
     "bronze": {
      "n": 4,
      "w": 1
     },
     "gold": {
      "n": 2,
      "w": 1
     },
     "platinum": {
      "n": 2,
      "w": 1
     }
    },
    "carry": {
     "platinum": {
      "n": 1,
      "w": 1
     }
    }
   }
  },
  "crunch": {
   "tiers": {
    "silver": {
     "n": 208,
     "w": 104
    },
    "platinum": {
     "n": 88,
     "w": 48
    },
    "diamond+": {
     "n": 9,
     "w": 4
    },
    "bronze": {
     "n": 169,
     "w": 86
    },
    "gold": {
     "n": 148,
     "w": 75
    }
   },
   "byRole": {
    "offlane": {
     "silver": {
      "n": 106,
      "w": 55
     },
     "platinum": {
      "n": 52,
      "w": 27
     },
     "diamond+": {
      "n": 6,
      "w": 2
     },
     "bronze": {
      "n": 87,
      "w": 46
     },
     "gold": {
      "n": 74,
      "w": 34
     }
    },
    "jungle": {
     "silver": {
      "n": 101,
      "w": 49
     },
     "bronze": {
      "n": 81,
      "w": 39
     },
     "platinum": {
      "n": 36,
      "w": 21
     },
     "gold": {
      "n": 74,
      "w": 41
     },
     "diamond+": {
      "n": 3,
      "w": 2
     }
    },
    "support": {
     "bronze": {
      "n": 1,
      "w": 1
     }
    },
    "carry": {
     "silver": {
      "n": 1,
      "w": 0
     }
    }
   }
  },
  "dekker": {
   "tiers": {
    "silver": {
     "n": 371,
     "w": 151
    },
    "bronze": {
     "n": 358,
     "w": 177
    },
    "gold": {
     "n": 202,
     "w": 106
    },
    "platinum": {
     "n": 81,
     "w": 36
    },
    "diamond+": {
     "n": 9,
     "w": 4
    }
   },
   "byRole": {
    "support": {
     "silver": {
      "n": 364,
      "w": 147
     },
     "bronze": {
      "n": 341,
      "w": 169
     },
     "gold": {
      "n": 195,
      "w": 100
     },
     "platinum": {
      "n": 73,
      "w": 32
     },
     "diamond+": {
      "n": 7,
      "w": 3
     }
    },
    "offlane": {
     "bronze": {
      "n": 10,
      "w": 4
     },
     "silver": {
      "n": 3,
      "w": 2
     },
     "platinum": {
      "n": 5,
      "w": 3
     },
     "diamond+": {
      "n": 1,
      "w": 1
     },
     "gold": {
      "n": 1,
      "w": 0
     }
    },
    "midlane": {
     "silver": {
      "n": 3,
      "w": 2
     },
     "diamond+": {
      "n": 1,
      "w": 0
     },
     "bronze": {
      "n": 5,
      "w": 3
     },
     "platinum": {
      "n": 2,
      "w": 0
     },
     "gold": {
      "n": 6,
      "w": 6
     }
    },
    "carry": {
     "silver": {
      "n": 1,
      "w": 0
     },
     "bronze": {
      "n": 2,
      "w": 1
     }
    },
    "jungle": {
     "platinum": {
      "n": 1,
      "w": 1
     }
    }
   }
  },
  "drongo": {
   "tiers": {
    "gold": {
     "n": 212,
     "w": 108
    },
    "silver": {
     "n": 377,
     "w": 177
    },
    "bronze": {
     "n": 239,
     "w": 120
    },
    "platinum": {
     "n": 60,
     "w": 29
    },
    "diamond+": {
     "n": 3,
     "w": 2
    }
   },
   "byRole": {
    "offlane": {
     "gold": {
      "n": 4,
      "w": 2
     },
     "bronze": {
      "n": 8,
      "w": 2
     },
     "silver": {
      "n": 5,
      "w": 3
     },
     "platinum": {
      "n": 1,
      "w": 1
     }
    },
    "carry": {
     "silver": {
      "n": 355,
      "w": 167
     },
     "gold": {
      "n": 199,
      "w": 101
     },
     "bronze": {
      "n": 205,
      "w": 104
     },
     "platinum": {
      "n": 58,
      "w": 27
     },
     "diamond+": {
      "n": 2,
      "w": 1
     }
    },
    "support": {
     "silver": {
      "n": 6,
      "w": 3
     },
     "bronze": {
      "n": 9,
      "w": 4
     },
     "platinum": {
      "n": 1,
      "w": 1
     },
     "gold": {
      "n": 1,
      "w": 0
     }
    },
    "midlane": {
     "bronze": {
      "n": 17,
      "w": 10
     },
     "silver": {
      "n": 10,
      "w": 4
     },
     "gold": {
      "n": 8,
      "w": 5
     },
     "diamond+": {
      "n": 1,
      "w": 1
     }
    },
    "jungle": {
     "silver": {
      "n": 1,
      "w": 0
     }
    }
   }
  },
  "eden": {
   "tiers": {
    "silver": {
     "n": 212,
     "w": 95
    },
    "platinum": {
     "n": 107,
     "w": 60
    },
    "bronze": {
     "n": 183,
     "w": 82
    },
    "gold": {
     "n": 133,
     "w": 62
    },
    "diamond+": {
     "n": 17,
     "w": 12
    }
   },
   "byRole": {
    "carry": {
     "silver": {
      "n": 152,
      "w": 70
     },
     "platinum": {
      "n": 78,
      "w": 47
     },
     "bronze": {
      "n": 132,
      "w": 61
     },
     "gold": {
      "n": 89,
      "w": 37
     },
     "diamond+": {
      "n": 11,
      "w": 8
     }
    },
    "offlane": {
     "platinum": {
      "n": 12,
      "w": 3
     },
     "silver": {
      "n": 40,
      "w": 15
     },
     "bronze": {
      "n": 34,
      "w": 14
     },
     "gold": {
      "n": 29,
      "w": 17
     },
     "diamond+": {
      "n": 1,
      "w": 1
     }
    },
    "midlane": {
     "silver": {
      "n": 14,
      "w": 7
     },
     "bronze": {
      "n": 6,
      "w": 3
     },
     "platinum": {
      "n": 13,
      "w": 8
     },
     "diamond+": {
      "n": 4,
      "w": 2
     },
     "gold": {
      "n": 8,
      "w": 3
     }
    },
    "support": {
     "bronze": {
      "n": 3,
      "w": 1
     },
     "silver": {
      "n": 4,
      "w": 3
     }
    },
    "jungle": {
     "silver": {
      "n": 2,
      "w": 0
     },
     "gold": {
      "n": 7,
      "w": 5
     },
     "platinum": {
      "n": 4,
      "w": 2
     },
     "bronze": {
      "n": 8,
      "w": 3
     },
     "diamond+": {
      "n": 1,
      "w": 1
     }
    }
   }
  },
  "feng-mao": {
   "tiers": {
    "gold": {
     "n": 190,
     "w": 86
    },
    "silver": {
     "n": 226,
     "w": 111
    },
    "bronze": {
     "n": 117,
     "w": 60
    },
    "platinum": {
     "n": 99,
     "w": 45
    },
    "diamond+": {
     "n": 16,
     "w": 9
    }
   },
   "byRole": {
    "jungle": {
     "gold": {
      "n": 160,
      "w": 74
     },
     "silver": {
      "n": 184,
      "w": 95
     },
     "platinum": {
      "n": 85,
      "w": 38
     },
     "bronze": {
      "n": 77,
      "w": 39
     },
     "diamond+": {
      "n": 9,
      "w": 8
     }
    },
    "offlane": {
     "bronze": {
      "n": 37,
      "w": 18
     },
     "silver": {
      "n": 34,
      "w": 11
     },
     "gold": {
      "n": 27,
      "w": 9
     },
     "platinum": {
      "n": 11,
      "w": 6
     },
     "diamond+": {
      "n": 3,
      "w": 1
     }
    },
    "midlane": {
     "platinum": {
      "n": 3,
      "w": 1
     },
     "silver": {
      "n": 3,
      "w": 2
     },
     "gold": {
      "n": 3,
      "w": 3
     },
     "diamond+": {
      "n": 2,
      "w": 0
     },
     "bronze": {
      "n": 1,
      "w": 1
     }
    },
    "support": {
     "silver": {
      "n": 3,
      "w": 2
     },
     "bronze": {
      "n": 2,
      "w": 2
     },
     "diamond+": {
      "n": 2,
      "w": 0
     }
    },
    "carry": {
     "silver": {
      "n": 2,
      "w": 1
     }
    }
   }
  },
  "gadget": {
   "tiers": {
    "gold": {
     "n": 157,
     "w": 90
    },
    "silver": {
     "n": 247,
     "w": 121
    },
    "platinum": {
     "n": 70,
     "w": 29
    },
    "bronze": {
     "n": 199,
     "w": 92
    },
    "diamond+": {
     "n": 9,
     "w": 4
    }
   },
   "byRole": {
    "support": {
     "gold": {
      "n": 29,
      "w": 16
     },
     "silver": {
      "n": 35,
      "w": 21
     },
     "bronze": {
      "n": 39,
      "w": 17
     },
     "platinum": {
      "n": 9,
      "w": 4
     }
    },
    "midlane": {
     "platinum": {
      "n": 56,
      "w": 24
     },
     "silver": {
      "n": 193,
      "w": 90
     },
     "gold": {
      "n": 121,
      "w": 71
     },
     "bronze": {
      "n": 147,
      "w": 68
     },
     "diamond+": {
      "n": 9,
      "w": 4
     }
    },
    "offlane": {
     "bronze": {
      "n": 12,
      "w": 7
     },
     "silver": {
      "n": 17,
      "w": 9
     },
     "gold": {
      "n": 6,
      "w": 2
     },
     "platinum": {
      "n": 3,
      "w": 0
     }
    },
    "carry": {
     "platinum": {
      "n": 2,
      "w": 1
     },
     "silver": {
      "n": 2,
      "w": 1
     },
     "gold": {
      "n": 1,
      "w": 1
     }
    },
    "jungle": {
     "bronze": {
      "n": 1,
      "w": 0
     }
    }
   }
  },
  "gideon": {
   "tiers": {
    "bronze": {
     "n": 260,
     "w": 135
    },
    "silver": {
     "n": 349,
     "w": 166
    },
    "gold": {
     "n": 194,
     "w": 105
    },
    "platinum": {
     "n": 81,
     "w": 39
    },
    "diamond+": {
     "n": 10,
     "w": 5
    }
   },
   "byRole": {
    "midlane": {
     "bronze": {
      "n": 245,
      "w": 123
     },
     "silver": {
      "n": 332,
      "w": 158
     },
     "gold": {
      "n": 192,
      "w": 104
     },
     "platinum": {
      "n": 79,
      "w": 38
     },
     "diamond+": {
      "n": 10,
      "w": 5
     }
    },
    "carry": {
     "silver": {
      "n": 3,
      "w": 3
     },
     "bronze": {
      "n": 1,
      "w": 0
     },
     "platinum": {
      "n": 1,
      "w": 1
     }
    },
    "support": {
     "bronze": {
      "n": 7,
      "w": 6
     },
     "silver": {
      "n": 6,
      "w": 2
     },
     "platinum": {
      "n": 1,
      "w": 0
     }
    },
    "offlane": {
     "bronze": {
      "n": 7,
      "w": 6
     },
     "silver": {
      "n": 8,
      "w": 3
     },
     "gold": {
      "n": 2,
      "w": 1
     }
    }
   }
  },
  "greystone": {
   "tiers": {
    "bronze": {
     "n": 419,
     "w": 195
    },
    "gold": {
     "n": 199,
     "w": 94
    },
    "silver": {
     "n": 481,
     "w": 230
    },
    "platinum": {
     "n": 59,
     "w": 31
    },
    "diamond+": {
     "n": 2,
     "w": 0
    }
   },
   "byRole": {
    "offlane": {
     "bronze": {
      "n": 325,
      "w": 156
     },
     "gold": {
      "n": 159,
      "w": 77
     },
     "platinum": {
      "n": 50,
      "w": 28
     },
     "silver": {
      "n": 416,
      "w": 204
     },
     "diamond+": {
      "n": 2,
      "w": 0
     }
    },
    "jungle": {
     "gold": {
      "n": 35,
      "w": 14
     },
     "silver": {
      "n": 60,
      "w": 23
     },
     "bronze": {
      "n": 88,
      "w": 36
     },
     "platinum": {
      "n": 8,
      "w": 3
     }
    },
    "midlane": {
     "silver": {
      "n": 4,
      "w": 2
     },
     "gold": {
      "n": 2,
      "w": 2
     },
     "bronze": {
      "n": 3,
      "w": 1
     }
    },
    "support": {
     "platinum": {
      "n": 1,
      "w": 0
     },
     "gold": {
      "n": 2,
      "w": 1
     },
     "bronze": {
      "n": 3,
      "w": 2
     },
     "silver": {
      "n": 1,
      "w": 1
     }
    },
    "carry": {
     "gold": {
      "n": 1,
      "w": 0
     }
    }
   }
  },
  "grim-exe": {
   "tiers": {
    "bronze": {
     "n": 220,
     "w": 118
    },
    "silver": {
     "n": 322,
     "w": 156
    },
    "gold": {
     "n": 236,
     "w": 123
    },
    "platinum": {
     "n": 75,
     "w": 33
    },
    "diamond+": {
     "n": 14,
     "w": 7
    }
   },
   "byRole": {
    "carry": {
     "bronze": {
      "n": 192,
      "w": 105
     },
     "gold": {
      "n": 218,
      "w": 112
     },
     "platinum": {
      "n": 67,
      "w": 30
     },
     "silver": {
      "n": 289,
      "w": 142
     },
     "diamond+": {
      "n": 12,
      "w": 5
     }
    },
    "midlane": {
     "silver": {
      "n": 29,
      "w": 12
     },
     "gold": {
      "n": 15,
      "w": 8
     },
     "diamond+": {
      "n": 2,
      "w": 2
     },
     "bronze": {
      "n": 14,
      "w": 8
     },
     "platinum": {
      "n": 8,
      "w": 3
     }
    },
    "offlane": {
     "gold": {
      "n": 3,
      "w": 3
     },
     "bronze": {
      "n": 11,
      "w": 4
     },
     "silver": {
      "n": 3,
      "w": 2
     }
    },
    "support": {
     "bronze": {
      "n": 1,
      "w": 0
     }
    },
    "jungle": {
     "bronze": {
      "n": 2,
      "w": 1
     },
     "silver": {
      "n": 1,
      "w": 0
     }
    }
   }
  },
  "grux": {
   "tiers": {
    "silver": {
     "n": 546,
     "w": 283
    },
    "gold": {
     "n": 338,
     "w": 176
    },
    "platinum": {
     "n": 124,
     "w": 60
    },
    "bronze": {
     "n": 403,
     "w": 205
    },
    "diamond+": {
     "n": 7,
     "w": 1
    }
   },
   "byRole": {
    "offlane": {
     "silver": {
      "n": 353,
      "w": 189
     },
     "bronze": {
      "n": 281,
      "w": 149
     },
     "gold": {
      "n": 204,
      "w": 114
     },
     "platinum": {
      "n": 81,
      "w": 36
     },
     "diamond+": {
      "n": 5,
      "w": 1
     }
    },
    "jungle": {
     "gold": {
      "n": 116,
      "w": 53
     },
     "platinum": {
      "n": 38,
      "w": 22
     },
     "silver": {
      "n": 183,
      "w": 88
     },
     "bronze": {
      "n": 113,
      "w": 51
     },
     "diamond+": {
      "n": 2,
      "w": 0
     }
    },
    "support": {
     "gold": {
      "n": 13,
      "w": 5
     },
     "bronze": {
      "n": 6,
      "w": 3
     },
     "silver": {
      "n": 9,
      "w": 6
     },
     "platinum": {
      "n": 3,
      "w": 2
     }
    },
    "carry": {
     "bronze": {
      "n": 1,
      "w": 0
     }
    },
    "midlane": {
     "silver": {
      "n": 1,
      "w": 0
     },
     "platinum": {
      "n": 2,
      "w": 0
     },
     "gold": {
      "n": 5,
      "w": 4
     },
     "bronze": {
      "n": 2,
      "w": 2
     }
    }
   }
  },
  "howitzer": {
   "tiers": {
    "bronze": {
     "n": 142,
     "w": 78
    },
    "gold": {
     "n": 104,
     "w": 52
    },
    "platinum": {
     "n": 58,
     "w": 24
    },
    "silver": {
     "n": 185,
     "w": 96
    },
    "diamond+": {
     "n": 3,
     "w": 3
    }
   },
   "byRole": {
    "midlane": {
     "bronze": {
      "n": 123,
      "w": 64
     },
     "gold": {
      "n": 95,
      "w": 48
     },
     "platinum": {
      "n": 51,
      "w": 22
     },
     "silver": {
      "n": 149,
      "w": 76
     },
     "diamond+": {
      "n": 3,
      "w": 3
     }
    },
    "carry": {
     "bronze": {
      "n": 2,
      "w": 2
     },
     "silver": {
      "n": 4,
      "w": 1
     }
    },
    "support": {
     "platinum": {
      "n": 3,
      "w": 1
     },
     "gold": {
      "n": 5,
      "w": 2
     },
     "bronze": {
      "n": 13,
      "w": 9
     },
     "silver": {
      "n": 12,
      "w": 5
     }
    },
    "offlane": {
     "silver": {
      "n": 20,
      "w": 14
     },
     "platinum": {
      "n": 4,
      "w": 1
     },
     "bronze": {
      "n": 4,
      "w": 3
     },
     "gold": {
      "n": 4,
      "w": 2
     }
    }
   }
  },
  "iggy-scorch": {
   "tiers": {
    "bronze": {
     "n": 314,
     "w": 155
    },
    "silver": {
     "n": 380,
     "w": 187
    },
    "gold": {
     "n": 230,
     "w": 124
    },
    "platinum": {
     "n": 38,
     "w": 19
    },
    "diamond+": {
     "n": 3,
     "w": 0
    }
   },
   "byRole": {
    "midlane": {
     "bronze": {
      "n": 225,
      "w": 108
     },
     "silver": {
      "n": 239,
      "w": 110
     },
     "gold": {
      "n": 132,
      "w": 67
     },
     "platinum": {
      "n": 21,
      "w": 12
     },
     "diamond+": {
      "n": 1,
      "w": 0
     }
    },
    "offlane": {
     "silver": {
      "n": 125,
      "w": 69
     },
     "gold": {
      "n": 93,
      "w": 53
     },
     "bronze": {
      "n": 67,
      "w": 36
     },
     "platinum": {
      "n": 13,
      "w": 5
     },
     "diamond+": {
      "n": 2,
      "w": 0
     }
    },
    "support": {
     "silver": {
      "n": 12,
      "w": 7
     },
     "bronze": {
      "n": 18,
      "w": 8
     },
     "gold": {
      "n": 4,
      "w": 3
     }
    },
    "carry": {
     "silver": {
      "n": 4,
      "w": 1
     },
     "platinum": {
      "n": 2,
      "w": 1
     },
     "bronze": {
      "n": 1,
      "w": 0
     },
     "gold": {
      "n": 1,
      "w": 1
     }
    },
    "jungle": {
     "bronze": {
      "n": 3,
      "w": 3
     },
     "platinum": {
      "n": 2,
      "w": 1
     }
    }
   }
  },
  "ikra": {
   "tiers": {
    "platinum": {
     "n": 108,
     "w": 69
    },
    "silver": {
     "n": 555,
     "w": 283
    },
    "bronze": {
     "n": 330,
     "w": 164
    },
    "gold": {
     "n": 377,
     "w": 197
    },
    "diamond+": {
     "n": 11,
     "w": 9
    }
   },
   "byRole": {
    "midlane": {
     "platinum": {
      "n": 78,
      "w": 52
     },
     "silver": {
      "n": 389,
      "w": 200
     },
     "bronze": {
      "n": 206,
      "w": 96
     },
     "gold": {
      "n": 267,
      "w": 136
     },
     "diamond+": {
      "n": 8,
      "w": 6
     }
    },
    "support": {
     "bronze": {
      "n": 84,
      "w": 47
     },
     "silver": {
      "n": 112,
      "w": 53
     },
     "gold": {
      "n": 74,
      "w": 37
     },
     "platinum": {
      "n": 18,
      "w": 9
     },
     "diamond+": {
      "n": 1,
      "w": 1
     }
    },
    "carry": {
     "bronze": {
      "n": 15,
      "w": 9
     },
     "gold": {
      "n": 15,
      "w": 12
     },
     "platinum": {
      "n": 3,
      "w": 2
     },
     "silver": {
      "n": 18,
      "w": 11
     },
     "diamond+": {
      "n": 1,
      "w": 1
     }
    },
    "offlane": {
     "silver": {
      "n": 34,
      "w": 18
     },
     "bronze": {
      "n": 24,
      "w": 11
     },
     "gold": {
      "n": 20,
      "w": 12
     },
     "platinum": {
      "n": 9,
      "w": 6
     },
     "diamond+": {
      "n": 1,
      "w": 1
     }
    },
    "jungle": {
     "silver": {
      "n": 2,
      "w": 1
     },
     "gold": {
      "n": 1,
      "w": 0
     },
     "bronze": {
      "n": 1,
      "w": 1
     }
    }
   }
  },
  "kallari": {
   "tiers": {
    "bronze": {
     "n": 121,
     "w": 60
    },
    "gold": {
     "n": 154,
     "w": 81
    },
    "silver": {
     "n": 183,
     "w": 94
    },
    "platinum": {
     "n": 98,
     "w": 60
    },
    "diamond+": {
     "n": 5,
     "w": 3
    }
   },
   "byRole": {
    "jungle": {
     "bronze": {
      "n": 102,
      "w": 52
     },
     "gold": {
      "n": 153,
      "w": 81
     },
     "silver": {
      "n": 181,
      "w": 94
     },
     "platinum": {
      "n": 98,
      "w": 60
     },
     "diamond+": {
      "n": 5,
      "w": 3
     }
    },
    "offlane": {
     "silver": {
      "n": 1,
      "w": 0
     },
     "bronze": {
      "n": 4,
      "w": 4
     }
    },
    "midlane": {
     "bronze": {
      "n": 6,
      "w": 3
     },
     "gold": {
      "n": 1,
      "w": 0
     }
    },
    "support": {
     "silver": {
      "n": 1,
      "w": 0
     },
     "bronze": {
      "n": 7,
      "w": 0
     }
    },
    "carry": {
     "bronze": {
      "n": 2,
      "w": 1
     }
    }
   }
  },
  "khaimera": {
   "tiers": {
    "bronze": {
     "n": 576,
     "w": 304
    },
    "silver": {
     "n": 674,
     "w": 329
    },
    "gold": {
     "n": 427,
     "w": 221
    },
    "platinum": {
     "n": 100,
     "w": 43
    },
    "diamond+": {
     "n": 10,
     "w": 3
    }
   },
   "byRole": {
    "jungle": {
     "bronze": {
      "n": 534,
      "w": 280
     },
     "silver": {
      "n": 619,
      "w": 302
     },
     "gold": {
      "n": 385,
      "w": 199
     },
     "platinum": {
      "n": 89,
      "w": 39
     },
     "diamond+": {
      "n": 6,
      "w": 1
     }
    },
    "offlane": {
     "bronze": {
      "n": 30,
      "w": 20
     },
     "silver": {
      "n": 54,
      "w": 26
     },
     "gold": {
      "n": 39,
      "w": 20
     },
     "platinum": {
      "n": 11,
      "w": 4
     },
     "diamond+": {
      "n": 4,
      "w": 2
     }
    },
    "carry": {
     "bronze": {
      "n": 4,
      "w": 1
     },
     "gold": {
      "n": 1,
      "w": 1
     }
    },
    "midlane": {
     "bronze": {
      "n": 6,
      "w": 2
     },
     "gold": {
      "n": 1,
      "w": 0
     }
    },
    "support": {
     "bronze": {
      "n": 2,
      "w": 1
     },
     "gold": {
      "n": 1,
      "w": 1
     },
     "silver": {
      "n": 1,
      "w": 1
     }
    }
   }
  },
  "kira": {
   "tiers": {
    "platinum": {
     "n": 95,
     "w": 51
    },
    "silver": {
     "n": 257,
     "w": 127
    },
    "gold": {
     "n": 203,
     "w": 97
    },
    "bronze": {
     "n": 171,
     "w": 78
    },
    "diamond+": {
     "n": 13,
     "w": 9
    }
   },
   "byRole": {
    "carry": {
     "platinum": {
      "n": 90,
      "w": 48
     },
     "silver": {
      "n": 245,
      "w": 122
     },
     "gold": {
      "n": 196,
      "w": 94
     },
     "bronze": {
      "n": 162,
      "w": 76
     },
     "diamond+": {
      "n": 11,
      "w": 7
     }
    },
    "support": {
     "bronze": {
      "n": 5,
      "w": 1
     }
    },
    "midlane": {
     "gold": {
      "n": 5,
      "w": 2
     },
     "silver": {
      "n": 9,
      "w": 3
     },
     "platinum": {
      "n": 2,
      "w": 1
     },
     "diamond+": {
      "n": 2,
      "w": 2
     }
    },
    "offlane": {
     "silver": {
      "n": 3,
      "w": 2
     },
     "bronze": {
      "n": 4,
      "w": 1
     },
     "gold": {
      "n": 2,
      "w": 1
     },
     "platinum": {
      "n": 3,
      "w": 2
     }
    }
   }
  },
  "kwang": {
   "tiers": {
    "platinum": {
     "n": 57,
     "w": 30
    },
    "silver": {
     "n": 202,
     "w": 93
    },
    "bronze": {
     "n": 168,
     "w": 84
    },
    "gold": {
     "n": 157,
     "w": 77
    },
    "diamond+": {
     "n": 16,
     "w": 11
    }
   },
   "byRole": {
    "jungle": {
     "platinum": {
      "n": 19,
      "w": 12
     },
     "gold": {
      "n": 47,
      "w": 20
     },
     "bronze": {
      "n": 66,
      "w": 38
     },
     "silver": {
      "n": 52,
      "w": 22
     },
     "diamond+": {
      "n": 1,
      "w": 0
     }
    },
    "support": {
     "silver": {
      "n": 9,
      "w": 6
     },
     "bronze": {
      "n": 9,
      "w": 3
     },
     "gold": {
      "n": 9,
      "w": 5
     },
     "platinum": {
      "n": 4,
      "w": 1
     },
     "diamond+": {
      "n": 1,
      "w": 0
     }
    },
    "offlane": {
     "bronze": {
      "n": 93,
      "w": 43
     },
     "gold": {
      "n": 96,
      "w": 51
     },
     "silver": {
      "n": 136,
      "w": 61
     },
     "platinum": {
      "n": 33,
      "w": 17
     },
     "diamond+": {
      "n": 14,
      "w": 11
     }
    },
    "midlane": {
     "silver": {
      "n": 5,
      "w": 4
     },
     "gold": {
      "n": 5,
      "w": 1
     }
    },
    "carry": {
     "platinum": {
      "n": 1,
      "w": 0
     }
    }
   }
  },
  "legion": {
   "tiers": {
    "gold": {
     "n": 359,
     "w": 193
    },
    "bronze": {
     "n": 502,
     "w": 255
    },
    "silver": {
     "n": 599,
     "w": 295
    },
    "platinum": {
     "n": 88,
     "w": 52
    },
    "diamond+": {
     "n": 7,
     "w": 3
    }
   },
   "byRole": {
    "carry": {
     "gold": {
      "n": 310,
      "w": 168
     },
     "bronze": {
      "n": 398,
      "w": 210
     },
     "silver": {
      "n": 517,
      "w": 262
     },
     "platinum": {
      "n": 79,
      "w": 47
     },
     "diamond+": {
      "n": 6,
      "w": 2
     }
    },
    "midlane": {
     "silver": {
      "n": 33,
      "w": 14
     },
     "gold": {
      "n": 33,
      "w": 14
     },
     "bronze": {
      "n": 47,
      "w": 18
     },
     "platinum": {
      "n": 4,
      "w": 2
     }
    },
    "offlane": {
     "bronze": {
      "n": 41,
      "w": 21
     },
     "platinum": {
      "n": 3,
      "w": 3
     },
     "silver": {
      "n": 36,
      "w": 14
     },
     "gold": {
      "n": 7,
      "w": 5
     },
     "diamond+": {
      "n": 1,
      "w": 1
     }
    },
    "support": {
     "bronze": {
      "n": 16,
      "w": 6
     },
     "silver": {
      "n": 12,
      "w": 4
     },
     "gold": {
      "n": 8,
      "w": 5
     },
     "platinum": {
      "n": 2,
      "w": 0
     }
    },
    "jungle": {
     "silver": {
      "n": 1,
      "w": 1
     },
     "gold": {
      "n": 1,
      "w": 1
     }
    }
   }
  },
  "lt-belica": {
   "tiers": {
    "platinum": {
     "n": 64,
     "w": 38
    },
    "silver": {
     "n": 339,
     "w": 163
    },
    "bronze": {
     "n": 257,
     "w": 124
    },
    "gold": {
     "n": 198,
     "w": 95
    },
    "diamond+": {
     "n": 5,
     "w": 4
    }
   },
   "byRole": {
    "midlane": {
     "platinum": {
      "n": 43,
      "w": 26
     },
     "silver": {
      "n": 199,
      "w": 92
     },
     "bronze": {
      "n": 112,
      "w": 57
     },
     "gold": {
      "n": 106,
      "w": 50
     },
     "diamond+": {
      "n": 3,
      "w": 3
     }
    },
    "support": {
     "silver": {
      "n": 123,
      "w": 66
     },
     "bronze": {
      "n": 136,
      "w": 65
     },
     "gold": {
      "n": 76,
      "w": 38
     },
     "platinum": {
      "n": 20,
      "w": 12
     },
     "diamond+": {
      "n": 2,
      "w": 1
     }
    },
    "offlane": {
     "silver": {
      "n": 9,
      "w": 2
     },
     "bronze": {
      "n": 4,
      "w": 0
     },
     "gold": {
      "n": 2,
      "w": 0
     }
    },
    "carry": {
     "gold": {
      "n": 14,
      "w": 7
     },
     "bronze": {
      "n": 5,
      "w": 2
     },
     "silver": {
      "n": 7,
      "w": 3
     },
     "platinum": {
      "n": 1,
      "w": 0
     }
    },
    "jungle": {
     "silver": {
      "n": 1,
      "w": 0
     }
    }
   }
  },
  "maco": {
   "tiers": {
    "platinum": {
     "n": 62,
     "w": 33
    },
    "bronze": {
     "n": 98,
     "w": 52
    },
    "gold": {
     "n": 98,
     "w": 57
    },
    "silver": {
     "n": 111,
     "w": 51
    },
    "diamond+": {
     "n": 9,
     "w": 7
    }
   },
   "byRole": {
    "support": {
     "platinum": {
      "n": 51,
      "w": 29
     },
     "bronze": {
      "n": 86,
      "w": 45
     },
     "gold": {
      "n": 94,
      "w": 55
     },
     "silver": {
      "n": 102,
      "w": 49
     },
     "diamond+": {
      "n": 6,
      "w": 4
     }
    },
    "midlane": {
     "silver": {
      "n": 3,
      "w": 1
     },
     "bronze": {
      "n": 4,
      "w": 3
     },
     "platinum": {
      "n": 6,
      "w": 3
     },
     "gold": {
      "n": 1,
      "w": 0
     },
     "diamond+": {
      "n": 1,
      "w": 1
     }
    },
    "offlane": {
     "gold": {
      "n": 3,
      "w": 2
     },
     "diamond+": {
      "n": 2,
      "w": 2
     },
     "silver": {
      "n": 5,
      "w": 1
     },
     "bronze": {
      "n": 8,
      "w": 4
     },
     "platinum": {
      "n": 4,
      "w": 1
     }
    },
    "carry": {
     "silver": {
      "n": 1,
      "w": 0
     }
    },
    "jungle": {
     "platinum": {
      "n": 1,
      "w": 0
     }
    }
   }
  },
  "morigesh": {
   "tiers": {
    "silver": {
     "n": 150,
     "w": 68
    },
    "bronze": {
     "n": 157,
     "w": 62
    },
    "gold": {
     "n": 95,
     "w": 47
    },
    "platinum": {
     "n": 35,
     "w": 20
    }
   },
   "byRole": {
    "midlane": {
     "silver": {
      "n": 123,
      "w": 56
     },
     "bronze": {
      "n": 124,
      "w": 52
     },
     "gold": {
      "n": 68,
      "w": 32
     },
     "platinum": {
      "n": 24,
      "w": 13
     }
    },
    "offlane": {
     "platinum": {
      "n": 11,
      "w": 7
     },
     "gold": {
      "n": 19,
      "w": 10
     },
     "silver": {
      "n": 23,
      "w": 10
     },
     "bronze": {
      "n": 20,
      "w": 6
     }
    },
    "carry": {
     "bronze": {
      "n": 7,
      "w": 2
     },
     "silver": {
      "n": 1,
      "w": 1
     }
    },
    "support": {
     "gold": {
      "n": 8,
      "w": 5
     },
     "silver": {
      "n": 3,
      "w": 1
     },
     "bronze": {
      "n": 3,
      "w": 2
     }
    },
    "jungle": {
     "bronze": {
      "n": 3,
      "w": 0
     }
    }
   }
  },
  "mourn": {
   "tiers": {
    "platinum": {
     "n": 93,
     "w": 51
    },
    "silver": {
     "n": 293,
     "w": 139
    },
    "gold": {
     "n": 251,
     "w": 135
    },
    "bronze": {
     "n": 148,
     "w": 75
    },
    "diamond+": {
     "n": 5,
     "w": 5
    }
   },
   "byRole": {
    "support": {
     "platinum": {
      "n": 74,
      "w": 40
     },
     "silver": {
      "n": 246,
      "w": 119
     },
     "gold": {
      "n": 216,
      "w": 119
     },
     "bronze": {
      "n": 130,
      "w": 66
     },
     "diamond+": {
      "n": 5,
      "w": 5
     }
    },
    "midlane": {
     "platinum": {
      "n": 1,
      "w": 1
     },
     "silver": {
      "n": 5,
      "w": 4
     },
     "gold": {
      "n": 3,
      "w": 1
     }
    },
    "offlane": {
     "silver": {
      "n": 30,
      "w": 13
     },
     "platinum": {
      "n": 18,
      "w": 10
     },
     "bronze": {
      "n": 14,
      "w": 6
     },
     "gold": {
      "n": 29,
      "w": 15
     }
    },
    "jungle": {
     "silver": {
      "n": 12,
      "w": 3
     },
     "gold": {
      "n": 3,
      "w": 0
     },
     "bronze": {
      "n": 2,
      "w": 1
     }
    },
    "carry": {
     "bronze": {
      "n": 2,
      "w": 2
     }
    }
   }
  },
  "murdock": {
   "tiers": {
    "platinum": {
     "n": 138,
     "w": 60
    },
    "gold": {
     "n": 322,
     "w": 160
    },
    "silver": {
     "n": 471,
     "w": 208
    },
    "bronze": {
     "n": 327,
     "w": 153
    },
    "diamond+": {
     "n": 16,
     "w": 8
    }
   },
   "byRole": {
    "offlane": {
     "platinum": {
      "n": 9,
      "w": 4
     },
     "gold": {
      "n": 41,
      "w": 25
     },
     "silver": {
      "n": 63,
      "w": 28
     },
     "bronze": {
      "n": 60,
      "w": 26
     }
    },
    "midlane": {
     "bronze": {
      "n": 11,
      "w": 5
     },
     "diamond+": {
      "n": 1,
      "w": 0
     },
     "gold": {
      "n": 12,
      "w": 5
     },
     "silver": {
      "n": 4,
      "w": 4
     },
     "platinum": {
      "n": 4,
      "w": 1
     }
    },
    "carry": {
     "silver": {
      "n": 399,
      "w": 173
     },
     "platinum": {
      "n": 125,
      "w": 55
     },
     "bronze": {
      "n": 247,
      "w": 117
     },
     "gold": {
      "n": 269,
      "w": 130
     },
     "diamond+": {
      "n": 15,
      "w": 8
     }
    },
    "support": {
     "silver": {
      "n": 5,
      "w": 3
     },
     "bronze": {
      "n": 8,
      "w": 4
     }
    },
    "jungle": {
     "bronze": {
      "n": 1,
      "w": 1
     }
    }
   }
  },
  "muriel": {
   "tiers": {
    "gold": {
     "n": 95,
     "w": 48
    },
    "silver": {
     "n": 116,
     "w": 58
    },
    "bronze": {
     "n": 89,
     "w": 51
    },
    "platinum": {
     "n": 60,
     "w": 34
    },
    "diamond+": {
     "n": 11,
     "w": 7
    }
   },
   "byRole": {
    "offlane": {
     "gold": {
      "n": 1,
      "w": 1
     },
     "platinum": {
      "n": 2,
      "w": 0
     },
     "silver": {
      "n": 2,
      "w": 0
     },
     "bronze": {
      "n": 2,
      "w": 0
     }
    },
    "support": {
     "silver": {
      "n": 112,
      "w": 57
     },
     "bronze": {
      "n": 86,
      "w": 51
     },
     "gold": {
      "n": 93,
      "w": 47
     },
     "platinum": {
      "n": 57,
      "w": 34
     },
     "diamond+": {
      "n": 11,
      "w": 7
     }
    },
    "jungle": {
     "bronze": {
      "n": 1,
      "w": 0
     }
    },
    "midlane": {
     "silver": {
      "n": 2,
      "w": 1
     },
     "gold": {
      "n": 1,
      "w": 0
     }
    },
    "carry": {
     "platinum": {
      "n": 1,
      "w": 0
     }
    }
   }
  },
  "narbash": {
   "tiers": {
    "silver": {
     "n": 190,
     "w": 102
    },
    "gold": {
     "n": 109,
     "w": 56
    },
    "platinum": {
     "n": 44,
     "w": 21
    },
    "bronze": {
     "n": 133,
     "w": 65
    },
    "diamond+": {
     "n": 7,
     "w": 3
    }
   },
   "byRole": {
    "support": {
     "silver": {
      "n": 189,
      "w": 102
     },
     "gold": {
      "n": 105,
      "w": 53
     },
     "platinum": {
      "n": 43,
      "w": 21
     },
     "bronze": {
      "n": 126,
      "w": 62
     },
     "diamond+": {
      "n": 7,
      "w": 3
     }
    },
    "carry": {
     "platinum": {
      "n": 1,
      "w": 0
     }
    },
    "jungle": {
     "silver": {
      "n": 1,
      "w": 0
     },
     "gold": {
      "n": 1,
      "w": 1
     },
     "bronze": {
      "n": 6,
      "w": 3
     }
    },
    "offlane": {
     "gold": {
      "n": 3,
      "w": 2
     },
     "bronze": {
      "n": 1,
      "w": 0
     }
    }
   }
  },
  "neon": {
   "tiers": {
    "platinum": {
     "n": 79,
     "w": 37
    },
    "silver": {
     "n": 194,
     "w": 77
    },
    "diamond+": {
     "n": 10,
     "w": 3
    },
    "gold": {
     "n": 137,
     "w": 60
    },
    "bronze": {
     "n": 147,
     "w": 72
    }
   },
   "byRole": {
    "midlane": {
     "platinum": {
      "n": 78,
      "w": 36
     },
     "silver": {
      "n": 186,
      "w": 71
     },
     "diamond+": {
      "n": 10,
      "w": 3
     },
     "gold": {
      "n": 130,
      "w": 57
     },
     "bronze": {
      "n": 142,
      "w": 71
     }
    },
    "support": {
     "silver": {
      "n": 3,
      "w": 3
     },
     "gold": {
      "n": 4,
      "w": 2
     },
     "bronze": {
      "n": 2,
      "w": 1
     }
    },
    "carry": {
     "gold": {
      "n": 1,
      "w": 0
     },
     "silver": {
      "n": 2,
      "w": 1
     },
     "bronze": {
      "n": 1,
      "w": 0
     }
    },
    "offlane": {
     "gold": {
      "n": 2,
      "w": 1
     },
     "platinum": {
      "n": 1,
      "w": 1
     },
     "silver": {
      "n": 2,
      "w": 2
     },
     "bronze": {
      "n": 2,
      "w": 0
     }
    },
    "jungle": {
     "silver": {
      "n": 1,
      "w": 0
     }
    }
   }
  },
  "phase": {
   "tiers": {
    "silver": {
     "n": 478,
     "w": 237
    },
    "gold": {
     "n": 296,
     "w": 149
    },
    "platinum": {
     "n": 108,
     "w": 61
    },
    "bronze": {
     "n": 321,
     "w": 160
    },
    "diamond+": {
     "n": 2,
     "w": 2
    }
   },
   "byRole": {
    "support": {
     "silver": {
      "n": 467,
      "w": 234
     },
     "gold": {
      "n": 288,
      "w": 149
     },
     "platinum": {
      "n": 106,
      "w": 59
     },
     "bronze": {
      "n": 319,
      "w": 158
     },
     "diamond+": {
      "n": 2,
      "w": 2
     }
    },
    "carry": {
     "gold": {
      "n": 2,
      "w": 0
     },
     "silver": {
      "n": 6,
      "w": 2
     },
     "platinum": {
      "n": 1,
      "w": 1
     },
     "bronze": {
      "n": 2,
      "w": 2
     }
    },
    "offlane": {
     "gold": {
      "n": 3,
      "w": 0
     },
     "silver": {
      "n": 1,
      "w": 0
     }
    },
    "midlane": {
     "silver": {
      "n": 3,
      "w": 1
     },
     "gold": {
      "n": 3,
      "w": 0
     },
     "platinum": {
      "n": 1,
      "w": 1
     }
    },
    "jungle": {
     "silver": {
      "n": 1,
      "w": 0
     }
    }
   }
  },
  "rampage": {
   "tiers": {
    "bronze": {
     "n": 106,
     "w": 47
    },
    "silver": {
     "n": 253,
     "w": 138
    },
    "platinum": {
     "n": 97,
     "w": 55
    },
    "gold": {
     "n": 214,
     "w": 126
    },
    "diamond+": {
     "n": 23,
     "w": 15
    }
   },
   "byRole": {
    "jungle": {
     "bronze": {
      "n": 95,
      "w": 46
     },
     "silver": {
      "n": 222,
      "w": 119
     },
     "platinum": {
      "n": 86,
      "w": 50
     },
     "gold": {
      "n": 190,
      "w": 113
     },
     "diamond+": {
      "n": 18,
      "w": 10
     }
    },
    "support": {
     "platinum": {
      "n": 7,
      "w": 3
     },
     "silver": {
      "n": 7,
      "w": 4
     },
     "bronze": {
      "n": 3,
      "w": 0
     },
     "diamond+": {
      "n": 4,
      "w": 4
     },
     "gold": {
      "n": 5,
      "w": 1
     }
    },
    "offlane": {
     "silver": {
      "n": 23,
      "w": 14
     },
     "platinum": {
      "n": 4,
      "w": 2
     },
     "gold": {
      "n": 18,
      "w": 12
     },
     "bronze": {
      "n": 6,
      "w": 1
     },
     "diamond+": {
      "n": 1,
      "w": 1
     }
    },
    "midlane": {
     "gold": {
      "n": 1,
      "w": 0
     },
     "silver": {
      "n": 1,
      "w": 1
     },
     "bronze": {
      "n": 2,
      "w": 0
     }
    }
   }
  },
  "renna": {
   "tiers": {
    "platinum": {
     "n": 66,
     "w": 35
    },
    "silver": {
     "n": 458,
     "w": 234
    },
    "gold": {
     "n": 239,
     "w": 124
    },
    "bronze": {
     "n": 343,
     "w": 189
    },
    "diamond+": {
     "n": 6,
     "w": 5
    }
   },
   "byRole": {
    "midlane": {
     "platinum": {
      "n": 62,
      "w": 33
     },
     "silver": {
      "n": 427,
      "w": 216
     },
     "gold": {
      "n": 224,
      "w": 119
     },
     "bronze": {
      "n": 321,
      "w": 178
     },
     "diamond+": {
      "n": 6,
      "w": 5
     }
    },
    "support": {
     "silver": {
      "n": 27,
      "w": 15
     },
     "platinum": {
      "n": 4,
      "w": 2
     },
     "gold": {
      "n": 11,
      "w": 4
     },
     "bronze": {
      "n": 12,
      "w": 6
     }
    },
    "offlane": {
     "gold": {
      "n": 3,
      "w": 1
     },
     "bronze": {
      "n": 8,
      "w": 3
     },
     "silver": {
      "n": 4,
      "w": 3
     }
    },
    "carry": {
     "gold": {
      "n": 1,
      "w": 0
     },
     "bronze": {
      "n": 2,
      "w": 2
     }
    }
   }
  },
  "revenant": {
   "tiers": {
    "bronze": {
     "n": 214,
     "w": 102
    },
    "silver": {
     "n": 293,
     "w": 156
    },
    "gold": {
     "n": 227,
     "w": 103
    },
    "platinum": {
     "n": 126,
     "w": 63
    },
    "diamond+": {
     "n": 11,
     "w": 6
    }
   },
   "byRole": {
    "carry": {
     "bronze": {
      "n": 184,
      "w": 85
     },
     "silver": {
      "n": 259,
      "w": 141
     },
     "gold": {
      "n": 199,
      "w": 90
     },
     "platinum": {
      "n": 120,
      "w": 59
     },
     "diamond+": {
      "n": 9,
      "w": 5
     }
    },
    "midlane": {
     "gold": {
      "n": 17,
      "w": 8
     },
     "silver": {
      "n": 24,
      "w": 12
     },
     "bronze": {
      "n": 10,
      "w": 7
     },
     "platinum": {
      "n": 5,
      "w": 4
     },
     "diamond+": {
      "n": 2,
      "w": 1
     }
    },
    "support": {
     "silver": {
      "n": 2,
      "w": 0
     },
     "gold": {
      "n": 1,
      "w": 0
     },
     "bronze": {
      "n": 6,
      "w": 3
     }
    },
    "offlane": {
     "gold": {
      "n": 10,
      "w": 5
     },
     "bronze": {
      "n": 14,
      "w": 7
     },
     "silver": {
      "n": 8,
      "w": 3
     },
     "platinum": {
      "n": 1,
      "w": 0
     }
    }
   }
  },
  "riktor": {
   "tiers": {
    "silver": {
     "n": 414,
     "w": 202
    },
    "platinum": {
     "n": 134,
     "w": 54
    },
    "gold": {
     "n": 326,
     "w": 176
    },
    "bronze": {
     "n": 246,
     "w": 120
    },
    "diamond+": {
     "n": 12,
     "w": 8
    }
   },
   "byRole": {
    "offlane": {
     "silver": {
      "n": 45,
      "w": 23
     },
     "gold": {
      "n": 41,
      "w": 23
     },
     "platinum": {
      "n": 29,
      "w": 13
     },
     "bronze": {
      "n": 9,
      "w": 5
     },
     "diamond+": {
      "n": 1,
      "w": 0
     }
    },
    "jungle": {
     "platinum": {
      "n": 12,
      "w": 4
     },
     "silver": {
      "n": 40,
      "w": 17
     },
     "gold": {
      "n": 36,
      "w": 21
     },
     "bronze": {
      "n": 17,
      "w": 11
     },
     "diamond+": {
      "n": 1,
      "w": 0
     }
    },
    "support": {
     "gold": {
      "n": 247,
      "w": 131
     },
     "bronze": {
      "n": 220,
      "w": 104
     },
     "silver": {
      "n": 328,
      "w": 162
     },
     "platinum": {
      "n": 90,
      "w": 35
     },
     "diamond+": {
      "n": 10,
      "w": 8
     }
    },
    "carry": {
     "platinum": {
      "n": 3,
      "w": 2
     },
     "silver": {
      "n": 1,
      "w": 0
     }
    },
    "midlane": {
     "gold": {
      "n": 2,
      "w": 1
     }
    }
   }
  },
  "serath": {
   "tiers": {
    "silver": {
     "n": 396,
     "w": 218
    },
    "bronze": {
     "n": 333,
     "w": 158
    },
    "gold": {
     "n": 251,
     "w": 111
    },
    "platinum": {
     "n": 72,
     "w": 38
    },
    "diamond+": {
     "n": 1,
     "w": 1
    }
   },
   "byRole": {
    "jungle": {
     "silver": {
      "n": 357,
      "w": 199
     },
     "bronze": {
      "n": 281,
      "w": 139
     },
     "gold": {
      "n": 243,
      "w": 109
     },
     "platinum": {
      "n": 68,
      "w": 35
     },
     "diamond+": {
      "n": 1,
      "w": 1
     }
    },
    "offlane": {
     "silver": {
      "n": 39,
      "w": 19
     },
     "bronze": {
      "n": 50,
      "w": 17
     },
     "platinum": {
      "n": 4,
      "w": 3
     },
     "gold": {
      "n": 7,
      "w": 2
     }
    },
    "midlane": {
     "bronze": {
      "n": 1,
      "w": 1
     },
     "gold": {
      "n": 1,
      "w": 0
     }
    },
    "support": {
     "bronze": {
      "n": 1,
      "w": 1
     }
    }
   }
  },
  "sevarog": {
   "tiers": {
    "platinum": {
     "n": 35,
     "w": 22
    },
    "silver": {
     "n": 158,
     "w": 75
    },
    "bronze": {
     "n": 89,
     "w": 42
    },
    "gold": {
     "n": 84,
     "w": 37
    },
    "diamond+": {
     "n": 4,
     "w": 2
    }
   },
   "byRole": {
    "offlane": {
     "platinum": {
      "n": 29,
      "w": 18
     },
     "silver": {
      "n": 117,
      "w": 58
     },
     "gold": {
      "n": 64,
      "w": 26
     },
     "bronze": {
      "n": 61,
      "w": 29
     },
     "diamond+": {
      "n": 2,
      "w": 1
     }
    },
    "jungle": {
     "silver": {
      "n": 38,
      "w": 16
     },
     "bronze": {
      "n": 25,
      "w": 13
     },
     "platinum": {
      "n": 4,
      "w": 2
     },
     "diamond+": {
      "n": 2,
      "w": 1
     },
     "gold": {
      "n": 20,
      "w": 11
     }
    },
    "carry": {
     "silver": {
      "n": 1,
      "w": 1
     }
    },
    "midlane": {
     "bronze": {
      "n": 1,
      "w": 0
     },
     "silver": {
      "n": 1,
      "w": 0
     },
     "platinum": {
      "n": 2,
      "w": 2
     }
    },
    "support": {
     "silver": {
      "n": 1,
      "w": 0
     },
     "bronze": {
      "n": 2,
      "w": 0
     }
    }
   }
  },
  "shinbi": {
   "tiers": {
    "silver": {
     "n": 293,
     "w": 142
    },
    "bronze": {
     "n": 192,
     "w": 101
    },
    "gold": {
     "n": 186,
     "w": 89
    },
    "platinum": {
     "n": 133,
     "w": 61
    },
    "diamond+": {
     "n": 12,
     "w": 8
    }
   },
   "byRole": {
    "offlane": {
     "silver": {
      "n": 256,
      "w": 130
     },
     "bronze": {
      "n": 160,
      "w": 84
     },
     "gold": {
      "n": 164,
      "w": 77
     },
     "platinum": {
      "n": 111,
      "w": 53
     },
     "diamond+": {
      "n": 11,
      "w": 8
     }
    },
    "jungle": {
     "bronze": {
      "n": 26,
      "w": 14
     },
     "silver": {
      "n": 26,
      "w": 5
     },
     "platinum": {
      "n": 9,
      "w": 4
     },
     "gold": {
      "n": 16,
      "w": 9
     },
     "diamond+": {
      "n": 1,
      "w": 0
     }
    },
    "midlane": {
     "gold": {
      "n": 6,
      "w": 3
     },
     "bronze": {
      "n": 4,
      "w": 2
     },
     "platinum": {
      "n": 13,
      "w": 4
     },
     "silver": {
      "n": 11,
      "w": 7
     }
    },
    "carry": {
     "bronze": {
      "n": 1,
      "w": 0
     }
    },
    "support": {
     "bronze": {
      "n": 1,
      "w": 1
     }
    }
   }
  },
  "skylar": {
   "tiers": {
    "silver": {
     "n": 307,
     "w": 162
    },
    "bronze": {
     "n": 245,
     "w": 134
    },
    "gold": {
     "n": 175,
     "w": 88
    },
    "platinum": {
     "n": 85,
     "w": 46
    },
    "diamond+": {
     "n": 1,
     "w": 0
    }
   },
   "byRole": {
    "carry": {
     "silver": {
      "n": 262,
      "w": 134
     },
     "bronze": {
      "n": 191,
      "w": 104
     },
     "gold": {
      "n": 153,
      "w": 75
     },
     "platinum": {
      "n": 72,
      "w": 38
     },
     "diamond+": {
      "n": 1,
      "w": 0
     }
    },
    "midlane": {
     "gold": {
      "n": 14,
      "w": 8
     },
     "silver": {
      "n": 25,
      "w": 14
     },
     "bronze": {
      "n": 28,
      "w": 16
     },
     "platinum": {
      "n": 12,
      "w": 7
     }
    },
    "offlane": {
     "bronze": {
      "n": 20,
      "w": 12
     },
     "silver": {
      "n": 17,
      "w": 13
     },
     "gold": {
      "n": 8,
      "w": 5
     },
     "platinum": {
      "n": 1,
      "w": 1
     }
    },
    "support": {
     "bronze": {
      "n": 6,
      "w": 2
     },
     "silver": {
      "n": 3,
      "w": 1
     }
    }
   }
  },
  "sparrow": {
   "tiers": {
    "platinum": {
     "n": 151,
     "w": 75
    },
    "gold": {
     "n": 422,
     "w": 220
    },
    "bronze": {
     "n": 544,
     "w": 281
    },
    "silver": {
     "n": 719,
     "w": 378
    },
    "diamond+": {
     "n": 9,
     "w": 4
    }
   },
   "byRole": {
    "carry": {
     "platinum": {
      "n": 148,
      "w": 73
     },
     "gold": {
      "n": 405,
      "w": 211
     },
     "bronze": {
      "n": 510,
      "w": 263
     },
     "silver": {
      "n": 685,
      "w": 366
     },
     "diamond+": {
      "n": 8,
      "w": 4
     }
    },
    "offlane": {
     "silver": {
      "n": 21,
      "w": 8
     },
     "bronze": {
      "n": 12,
      "w": 6
     },
     "platinum": {
      "n": 1,
      "w": 1
     },
     "gold": {
      "n": 6,
      "w": 1
     },
     "diamond+": {
      "n": 1,
      "w": 0
     }
    },
    "midlane": {
     "silver": {
      "n": 12,
      "w": 4
     },
     "bronze": {
      "n": 16,
      "w": 10
     },
     "gold": {
      "n": 9,
      "w": 6
     },
     "platinum": {
      "n": 2,
      "w": 1
     }
    },
    "support": {
     "bronze": {
      "n": 5,
      "w": 1
     },
     "silver": {
      "n": 1,
      "w": 0
     },
     "gold": {
      "n": 2,
      "w": 2
     }
    },
    "jungle": {
     "bronze": {
      "n": 1,
      "w": 1
     }
    }
   }
  },
  "steel": {
   "tiers": {
    "silver": {
     "n": 732,
     "w": 393
    },
    "gold": {
     "n": 427,
     "w": 217
    },
    "bronze": {
     "n": 437,
     "w": 222
    },
    "platinum": {
     "n": 143,
     "w": 71
    },
    "diamond+": {
     "n": 9,
     "w": 4
    }
   },
   "byRole": {
    "jungle": {
     "silver": {
      "n": 39,
      "w": 18
     },
     "bronze": {
      "n": 9,
      "w": 3
     },
     "gold": {
      "n": 18,
      "w": 14
     },
     "platinum": {
      "n": 2,
      "w": 0
     }
    },
    "support": {
     "gold": {
      "n": 298,
      "w": 147
     },
     "bronze": {
      "n": 327,
      "w": 174
     },
     "silver": {
      "n": 489,
      "w": 267
     },
     "platinum": {
      "n": 93,
      "w": 46
     },
     "diamond+": {
      "n": 8,
      "w": 4
     }
    },
    "offlane": {
     "platinum": {
      "n": 48,
      "w": 25
     },
     "gold": {
      "n": 110,
      "w": 55
     },
     "bronze": {
      "n": 100,
      "w": 45
     },
     "silver": {
      "n": 201,
      "w": 108
     },
     "diamond+": {
      "n": 1,
      "w": 0
     }
    },
    "carry": {
     "silver": {
      "n": 3,
      "w": 0
     },
     "bronze": {
      "n": 1,
      "w": 0
     }
    },
    "midlane": {
     "gold": {
      "n": 1,
      "w": 1
     }
    }
   }
  },
  "terra": {
   "tiers": {
    "gold": {
     "n": 158,
     "w": 65
    },
    "silver": {
     "n": 169,
     "w": 91
    },
    "bronze": {
     "n": 133,
     "w": 62
    },
    "platinum": {
     "n": 53,
     "w": 24
    },
    "diamond+": {
     "n": 5,
     "w": 3
    }
   },
   "byRole": {
    "offlane": {
     "gold": {
      "n": 118,
      "w": 48
     },
     "silver": {
      "n": 139,
      "w": 78
     },
     "bronze": {
      "n": 104,
      "w": 48
     },
     "platinum": {
      "n": 48,
      "w": 22
     },
     "diamond+": {
      "n": 4,
      "w": 3
     }
    },
    "support": {
     "gold": {
      "n": 5,
      "w": 4
     },
     "bronze": {
      "n": 6,
      "w": 2
     },
     "silver": {
      "n": 6,
      "w": 1
     },
     "platinum": {
      "n": 3,
      "w": 1
     }
    },
    "jungle": {
     "silver": {
      "n": 23,
      "w": 12
     },
     "bronze": {
      "n": 19,
      "w": 10
     },
     "gold": {
      "n": 32,
      "w": 11
     },
     "diamond+": {
      "n": 1,
      "w": 0
     },
     "platinum": {
      "n": 2,
      "w": 1
     }
    },
    "midlane": {
     "bronze": {
      "n": 4,
      "w": 2
     },
     "gold": {
      "n": 3,
      "w": 2
     },
     "silver": {
      "n": 1,
      "w": 0
     }
    }
   }
  },
  "the-fey": {
   "tiers": {
    "silver": {
     "n": 548,
     "w": 269
    },
    "platinum": {
     "n": 147,
     "w": 80
    },
    "gold": {
     "n": 377,
     "w": 191
    },
    "bronze": {
     "n": 283,
     "w": 143
    },
    "diamond+": {
     "n": 7,
     "w": 3
    }
   },
   "byRole": {
    "midlane": {
     "silver": {
      "n": 467,
      "w": 230
     },
     "platinum": {
      "n": 131,
      "w": 74
     },
     "bronze": {
      "n": 233,
      "w": 120
     },
     "gold": {
      "n": 334,
      "w": 173
     },
     "diamond+": {
      "n": 4,
      "w": 2
     }
    },
    "support": {
     "platinum": {
      "n": 13,
      "w": 5
     },
     "gold": {
      "n": 33,
      "w": 13
     },
     "silver": {
      "n": 69,
      "w": 32
     },
     "bronze": {
      "n": 41,
      "w": 19
     },
     "diamond+": {
      "n": 3,
      "w": 1
     }
    },
    "carry": {
     "bronze": {
      "n": 3,
      "w": 1
     },
     "gold": {
      "n": 6,
      "w": 3
     },
     "platinum": {
      "n": 1,
      "w": 0
     },
     "silver": {
      "n": 3,
      "w": 3
     }
    },
    "offlane": {
     "bronze": {
      "n": 6,
      "w": 3
     },
     "platinum": {
      "n": 2,
      "w": 1
     },
     "silver": {
      "n": 9,
      "w": 4
     },
     "gold": {
      "n": 4,
      "w": 2
     }
    }
   }
  },
  "twinblast": {
   "tiers": {
    "gold": {
     "n": 176,
     "w": 99
    },
    "silver": {
     "n": 223,
     "w": 106
    },
    "bronze": {
     "n": 202,
     "w": 91
    },
    "platinum": {
     "n": 72,
     "w": 39
    },
    "diamond+": {
     "n": 3,
     "w": 2
    }
   },
   "byRole": {
    "carry": {
     "gold": {
      "n": 159,
      "w": 86
     },
     "silver": {
      "n": 195,
      "w": 95
     },
     "bronze": {
      "n": 179,
      "w": 80
     },
     "platinum": {
      "n": 63,
      "w": 34
     },
     "diamond+": {
      "n": 3,
      "w": 2
     }
    },
    "offlane": {
     "gold": {
      "n": 9,
      "w": 7
     },
     "bronze": {
      "n": 15,
      "w": 7
     },
     "silver": {
      "n": 15,
      "w": 5
     },
     "platinum": {
      "n": 1,
      "w": 1
     }
    },
    "midlane": {
     "platinum": {
      "n": 8,
      "w": 4
     },
     "silver": {
      "n": 11,
      "w": 6
     },
     "gold": {
      "n": 7,
      "w": 5
     },
     "bronze": {
      "n": 4,
      "w": 2
     }
    },
    "support": {
     "bronze": {
      "n": 4,
      "w": 2
     },
     "silver": {
      "n": 2,
      "w": 0
     },
     "gold": {
      "n": 1,
      "w": 1
     }
    }
   }
  },
  "wraith": {
   "tiers": {
    "platinum": {
     "n": 81,
     "w": 32
    },
    "bronze": {
     "n": 133,
     "w": 64
    },
    "silver": {
     "n": 240,
     "w": 109
    },
    "gold": {
     "n": 187,
     "w": 89
    },
    "diamond+": {
     "n": 5,
     "w": 3
    }
   },
   "byRole": {
    "midlane": {
     "platinum": {
      "n": 48,
      "w": 21
     },
     "silver": {
      "n": 126,
      "w": 55
     },
     "gold": {
      "n": 111,
      "w": 53
     },
     "bronze": {
      "n": 82,
      "w": 38
     },
     "diamond+": {
      "n": 4,
      "w": 2
     }
    },
    "carry": {
     "bronze": {
      "n": 39,
      "w": 19
     },
     "silver": {
      "n": 81,
      "w": 37
     },
     "platinum": {
      "n": 14,
      "w": 4
     },
     "gold": {
      "n": 50,
      "w": 23
     },
     "diamond+": {
      "n": 1,
      "w": 1
     }
    },
    "support": {
     "gold": {
      "n": 24,
      "w": 13
     },
     "platinum": {
      "n": 17,
      "w": 7
     },
     "bronze": {
      "n": 11,
      "w": 6
     },
     "silver": {
      "n": 30,
      "w": 15
     }
    },
    "offlane": {
     "platinum": {
      "n": 2,
      "w": 0
     },
     "silver": {
      "n": 3,
      "w": 2
     },
     "gold": {
      "n": 2,
      "w": 0
     },
     "bronze": {
      "n": 1,
      "w": 1
     }
    }
   }
  },
  "wukong": {
   "tiers": {
    "bronze": {
     "n": 78,
     "w": 29
    },
    "platinum": {
     "n": 40,
     "w": 16
    },
    "silver": {
     "n": 85,
     "w": 42
    },
    "gold": {
     "n": 58,
     "w": 27
    },
    "diamond+": {
     "n": 6,
     "w": 5
    }
   },
   "byRole": {
    "jungle": {
     "bronze": {
      "n": 56,
      "w": 18
     },
     "platinum": {
      "n": 29,
      "w": 10
     },
     "silver": {
      "n": 49,
      "w": 23
     },
     "gold": {
      "n": 36,
      "w": 17
     },
     "diamond+": {
      "n": 2,
      "w": 1
     }
    },
    "support": {
     "bronze": {
      "n": 3,
      "w": 0
     },
     "gold": {
      "n": 2,
      "w": 2
     },
     "silver": {
      "n": 8,
      "w": 5
     },
     "platinum": {
      "n": 1,
      "w": 0
     }
    },
    "offlane": {
     "silver": {
      "n": 24,
      "w": 14
     },
     "platinum": {
      "n": 9,
      "w": 6
     },
     "bronze": {
      "n": 16,
      "w": 11
     },
     "gold": {
      "n": 19,
      "w": 7
     },
     "diamond+": {
      "n": 4,
      "w": 4
     }
    },
    "midlane": {
     "silver": {
      "n": 4,
      "w": 0
     },
     "gold": {
      "n": 1,
      "w": 1
     },
     "bronze": {
      "n": 3,
      "w": 0
     },
     "platinum": {
      "n": 1,
      "w": 0
     }
    }
   }
  },
  "yin": {
   "tiers": {
    "silver": {
     "n": 216,
     "w": 108
    },
    "platinum": {
     "n": 39,
     "w": 21
    },
    "bronze": {
     "n": 177,
     "w": 85
    },
    "gold": {
     "n": 143,
     "w": 74
    },
    "diamond+": {
     "n": 3,
     "w": 2
    }
   },
   "byRole": {
    "offlane": {
     "silver": {
      "n": 61,
      "w": 30
     },
     "gold": {
      "n": 32,
      "w": 14
     },
     "bronze": {
      "n": 25,
      "w": 16
     },
     "platinum": {
      "n": 7,
      "w": 6
     }
    },
    "jungle": {
     "silver": {
      "n": 146,
      "w": 71
     },
     "platinum": {
      "n": 29,
      "w": 13
     },
     "bronze": {
      "n": 137,
      "w": 65
     },
     "gold": {
      "n": 104,
      "w": 57
     },
     "diamond+": {
      "n": 3,
      "w": 2
     }
    },
    "midlane": {
     "silver": {
      "n": 3,
      "w": 2
     },
     "gold": {
      "n": 3,
      "w": 1
     },
     "bronze": {
      "n": 6,
      "w": 3
     },
     "platinum": {
      "n": 3,
      "w": 2
     }
    },
    "support": {
     "silver": {
      "n": 1,
      "w": 1
     },
     "bronze": {
      "n": 2,
      "w": 0
     }
    },
    "carry": {
     "bronze": {
      "n": 7,
      "w": 1
     },
     "gold": {
      "n": 4,
      "w": 2
     },
     "silver": {
      "n": 5,
      "w": 4
     }
    }
   }
  },
  "yurei": {
   "tiers": {
    "bronze": {
     "n": 143,
     "w": 71
    },
    "gold": {
     "n": 92,
     "w": 36
    },
    "diamond+": {
     "n": 10,
     "w": 8
    },
    "silver": {
     "n": 125,
     "w": 47
    },
    "platinum": {
     "n": 65,
     "w": 30
    }
   },
   "byRole": {
    "jungle": {
     "bronze": {
      "n": 130,
      "w": 65
     },
     "gold": {
      "n": 67,
      "w": 28
     },
     "diamond+": {
      "n": 9,
      "w": 7
     },
     "silver": {
      "n": 104,
      "w": 39
     },
     "platinum": {
      "n": 51,
      "w": 27
     }
    },
    "support": {
     "bronze": {
      "n": 1,
      "w": 1
     },
     "gold": {
      "n": 1,
      "w": 1
     },
     "silver": {
      "n": 1,
      "w": 0
     }
    },
    "offlane": {
     "bronze": {
      "n": 11,
      "w": 4
     },
     "platinum": {
      "n": 11,
      "w": 3
     },
     "gold": {
      "n": 22,
      "w": 6
     },
     "diamond+": {
      "n": 1,
      "w": 1
     },
     "silver": {
      "n": 19,
      "w": 8
     }
    },
    "midlane": {
     "platinum": {
      "n": 1,
      "w": 0
     },
     "silver": {
      "n": 1,
      "w": 0
     },
     "gold": {
      "n": 2,
      "w": 1
     },
     "bronze": {
      "n": 1,
      "w": 1
     }
    },
    "carry": {
     "platinum": {
      "n": 2,
      "w": 0
     }
    }
   }
  },
  "zarus": {
   "tiers": {
    "silver": {
     "n": 356,
     "w": 171
    },
    "gold": {
     "n": 279,
     "w": 129
    },
    "diamond+": {
     "n": 16,
     "w": 6
    },
    "bronze": {
     "n": 214,
     "w": 114
    },
    "platinum": {
     "n": 159,
     "w": 87
    }
   },
   "byRole": {
    "jungle": {
     "silver": {
      "n": 207,
      "w": 101
     },
     "gold": {
      "n": 192,
      "w": 86
     },
     "diamond+": {
      "n": 9,
      "w": 4
     },
     "bronze": {
      "n": 110,
      "w": 67
     },
     "platinum": {
      "n": 105,
      "w": 58
     }
    },
    "offlane": {
     "silver": {
      "n": 147,
      "w": 69
     },
     "gold": {
      "n": 84,
      "w": 42
     },
     "bronze": {
      "n": 102,
      "w": 46
     },
     "platinum": {
      "n": 49,
      "w": 28
     },
     "diamond+": {
      "n": 5,
      "w": 2
     }
    },
    "support": {
     "diamond+": {
      "n": 2,
      "w": 0
     },
     "silver": {
      "n": 2,
      "w": 1
     },
     "bronze": {
      "n": 2,
      "w": 1
     },
     "platinum": {
      "n": 5,
      "w": 1
     },
     "gold": {
      "n": 3,
      "w": 1
     }
    }
   }
  },
  "zinx": {
   "tiers": {
    "silver": {
     "n": 387,
     "w": 205
    },
    "bronze": {
     "n": 366,
     "w": 184
    },
    "gold": {
     "n": 208,
     "w": 88
    },
    "platinum": {
     "n": 52,
     "w": 20
    },
    "diamond+": {
     "n": 7,
     "w": 3
    }
   },
   "byRole": {
    "carry": {
     "silver": {
      "n": 24,
      "w": 12
     },
     "gold": {
      "n": 22,
      "w": 9
     },
     "bronze": {
      "n": 12,
      "w": 6
     },
     "platinum": {
      "n": 2,
      "w": 1
     },
     "diamond+": {
      "n": 1,
      "w": 0
     }
    },
    "support": {
     "silver": {
      "n": 250,
      "w": 125
     },
     "bronze": {
      "n": 284,
      "w": 134
     },
     "gold": {
      "n": 122,
      "w": 45
     },
     "platinum": {
      "n": 30,
      "w": 9
     },
     "diamond+": {
      "n": 1,
      "w": 0
     }
    },
    "offlane": {
     "silver": {
      "n": 71,
      "w": 43
     },
     "gold": {
      "n": 36,
      "w": 21
     },
     "platinum": {
      "n": 10,
      "w": 6
     },
     "bronze": {
      "n": 59,
      "w": 35
     },
     "diamond+": {
      "n": 2,
      "w": 2
     }
    },
    "midlane": {
     "bronze": {
      "n": 10,
      "w": 8
     },
     "gold": {
      "n": 28,
      "w": 13
     },
     "platinum": {
      "n": 9,
      "w": 3
     },
     "silver": {
      "n": 40,
      "w": 24
     },
     "diamond+": {
      "n": 3,
      "w": 1
     }
    },
    "jungle": {
     "platinum": {
      "n": 1,
      "w": 1
     },
     "bronze": {
      "n": 1,
      "w": 1
     },
     "silver": {
      "n": 2,
      "w": 1
     }
    }
   }
  }
 }
}