{
 "meta": {
  "source": "omeda.city matches.json (official Omeda public API), ranked rows only",
  "generatedAt": "2026-07-12T03:17:46.754Z",
  "windowHours": 36,
  "pages": 120,
  "matches": 4683,
  "buckets": {
   "low": {
    "label": "Bronze–Gold",
    "rule": "row rank 10–39",
    "playerRows": 41907
   },
   "high": {
    "label": "Platinum+",
    "rule": "row rank >= 40",
    "playerRows": 4923
   }
  },
  "note": "bucketed per PLAYER ROW by that player’s own rank (a mixed-tier match feeds both buckets); rows with no rank dropped"
 },
 "heroes": {
  "adele": {
   "low": {
    "n": 735,
    "w": 348
   },
   "high": {
    "n": 85,
    "w": 45
   },
   "byRole": {
    "support": {
     "low": {
      "n": 455,
      "w": 229
     },
     "high": {
      "n": 71,
      "w": 39
     }
    },
    "offlane": {
     "low": {
      "n": 242,
      "w": 108
     },
     "high": {
      "n": 14,
      "w": 6
     }
    },
    "jungle": {
     "low": {
      "n": 35,
      "w": 11
     },
     "high": {
      "n": 0,
      "w": 0
     }
    },
    "midlane": {
     "low": {
      "n": 2,
      "w": 0
     },
     "high": {
      "n": 0,
      "w": 0
     }
    },
    "carry": {
     "low": {
      "n": 1,
      "w": 0
     },
     "high": {
      "n": 0,
      "w": 0
     }
    }
   }
  },
  "akeron": {
   "low": {
    "n": 389,
    "w": 178
   },
   "high": {
    "n": 78,
    "w": 44
   },
   "byRole": {
    "offlane": {
     "low": {
      "n": 275,
      "w": 133
     },
     "high": {
      "n": 48,
      "w": 30
     }
    },
    "support": {
     "low": {
      "n": 20,
      "w": 12
     },
     "high": {
      "n": 5,
      "w": 3
     }
    },
    "jungle": {
     "low": {
      "n": 83,
      "w": 30
     },
     "high": {
      "n": 18,
      "w": 10
     }
    },
    "midlane": {
     "low": {
      "n": 11,
      "w": 3
     },
     "high": {
      "n": 7,
      "w": 1
     }
    }
   }
  },
  "argus": {
   "low": {
    "n": 1161,
    "w": 587
   },
   "high": {
    "n": 132,
    "w": 68
   },
   "byRole": {
    "support": {
     "low": {
      "n": 366,
      "w": 165
     },
     "high": {
      "n": 13,
      "w": 5
     }
    },
    "midlane": {
     "low": {
      "n": 761,
      "w": 408
     },
     "high": {
      "n": 118,
      "w": 63
     }
    },
    "offlane": {
     "low": {
      "n": 20,
      "w": 11
     },
     "high": {
      "n": 1,
      "w": 0
     }
    },
    "carry": {
     "low": {
      "n": 10,
      "w": 3
     },
     "high": {
      "n": 0,
      "w": 0
     }
    },
    "jungle": {
     "low": {
      "n": 4,
      "w": 0
     },
     "high": {
      "n": 0,
      "w": 0
     }
    }
   }
  },
  "aurora": {
   "low": {
    "n": 967,
    "w": 523
   },
   "high": {
    "n": 78,
    "w": 41
   },
   "byRole": {
    "offlane": {
     "low": {
      "n": 399,
      "w": 205
     },
     "high": {
      "n": 27,
      "w": 11
     }
    },
    "jungle": {
     "low": {
      "n": 409,
      "w": 222
     },
     "high": {
      "n": 38,
      "w": 21
     }
    },
    "support": {
     "low": {
      "n": 142,
      "w": 85
     },
     "high": {
      "n": 12,
      "w": 8
     }
    },
    "midlane": {
     "low": {
      "n": 16,
      "w": 11
     },
     "high": {
      "n": 1,
      "w": 1
     }
    },
    "carry": {
     "low": {
      "n": 1,
      "w": 0
     },
     "high": {
      "n": 0,
      "w": 0
     }
    }
   }
  },
  "bayle": {
   "low": {
    "n": 1326,
    "w": 674
   },
   "high": {
    "n": 107,
    "w": 47
   },
   "byRole": {
    "offlane": {
     "low": {
      "n": 916,
      "w": 481
     },
     "high": {
      "n": 83,
      "w": 35
     }
    },
    "jungle": {
     "low": {
      "n": 372,
      "w": 177
     },
     "high": {
      "n": 21,
      "w": 11
     }
    },
    "support": {
     "low": {
      "n": 31,
      "w": 16
     },
     "high": {
      "n": 3,
      "w": 1
     }
    },
    "midlane": {
     "low": {
      "n": 6,
      "w": 0
     },
     "high": {
      "n": 0,
      "w": 0
     }
    },
    "carry": {
     "low": {
      "n": 1,
      "w": 0
     },
     "high": {
      "n": 0,
      "w": 0
     }
    }
   }
  },
  "boris": {
   "low": {
    "n": 693,
    "w": 368
   },
   "high": {
    "n": 71,
    "w": 43
   },
   "byRole": {
    "jungle": {
     "low": {
      "n": 680,
      "w": 366
     },
     "high": {
      "n": 70,
      "w": 43
     }
    },
    "offlane": {
     "low": {
      "n": 11,
      "w": 1
     },
     "high": {
      "n": 1,
      "w": 0
     }
    },
    "support": {
     "low": {
      "n": 1,
      "w": 1
     },
     "high": {
      "n": 0,
      "w": 0
     }
    },
    "midlane": {
     "low": {
      "n": 1,
      "w": 0
     },
     "high": {
      "n": 0,
      "w": 0
     }
    }
   }
  },
  "countess": {
   "low": {
    "n": 716,
    "w": 332
   },
   "high": {
    "n": 89,
    "w": 51
   },
   "byRole": {
    "offlane": {
     "low": {
      "n": 198,
      "w": 91
     },
     "high": {
      "n": 27,
      "w": 19
     }
    },
    "midlane": {
     "low": {
      "n": 321,
      "w": 157
     },
     "high": {
      "n": 40,
      "w": 21
     }
    },
    "jungle": {
     "low": {
      "n": 183,
      "w": 79
     },
     "high": {
      "n": 19,
      "w": 9
     }
    },
    "support": {
     "low": {
      "n": 14,
      "w": 5
     },
     "high": {
      "n": 2,
      "w": 1
     }
    },
    "carry": {
     "low": {
      "n": 0,
      "w": 0
     },
     "high": {
      "n": 1,
      "w": 1
     }
    }
   }
  },
  "crunch": {
   "low": {
    "n": 517,
    "w": 257
   },
   "high": {
    "n": 96,
    "w": 51
   },
   "byRole": {
    "offlane": {
     "low": {
      "n": 263,
      "w": 131
     },
     "high": {
      "n": 57,
      "w": 28
     }
    },
    "jungle": {
     "low": {
      "n": 252,
      "w": 125
     },
     "high": {
      "n": 39,
      "w": 23
     }
    },
    "support": {
     "low": {
      "n": 1,
      "w": 1
     },
     "high": {
      "n": 0,
      "w": 0
     }
    },
    "carry": {
     "low": {
      "n": 1,
      "w": 0
     },
     "high": {
      "n": 0,
      "w": 0
     }
    }
   }
  },
  "dekker": {
   "low": {
    "n": 930,
    "w": 431
   },
   "high": {
    "n": 91,
    "w": 41
   },
   "byRole": {
    "support": {
     "low": {
      "n": 901,
      "w": 415
     },
     "high": {
      "n": 81,
      "w": 36
     }
    },
    "offlane": {
     "low": {
      "n": 14,
      "w": 6
     },
     "high": {
      "n": 6,
      "w": 4
     }
    },
    "midlane": {
     "low": {
      "n": 12,
      "w": 9
     },
     "high": {
      "n": 3,
      "w": 0
     }
    },
    "carry": {
     "low": {
      "n": 3,
      "w": 1
     },
     "high": {
      "n": 0,
      "w": 0
     }
    },
    "jungle": {
     "low": {
      "n": 0,
      "w": 0
     },
     "high": {
      "n": 1,
      "w": 1
     }
    }
   }
  },
  "drongo": {
   "low": {
    "n": 832,
    "w": 407
   },
   "high": {
    "n": 63,
    "w": 31
   },
   "byRole": {
    "carry": {
     "low": {
      "n": 762,
      "w": 373
     },
     "high": {
      "n": 60,
      "w": 28
     }
    },
    "offlane": {
     "low": {
      "n": 18,
      "w": 8
     },
     "high": {
      "n": 1,
      "w": 1
     }
    },
    "support": {
     "low": {
      "n": 16,
      "w": 7
     },
     "high": {
      "n": 1,
      "w": 1
     }
    },
    "midlane": {
     "low": {
      "n": 35,
      "w": 19
     },
     "high": {
      "n": 1,
      "w": 1
     }
    },
    "jungle": {
     "low": {
      "n": 1,
      "w": 0
     },
     "high": {
      "n": 0,
      "w": 0
     }
    }
   }
  },
  "eden": {
   "low": {
    "n": 528,
    "w": 239
   },
   "high": {
    "n": 122,
    "w": 71
   },
   "byRole": {
    "carry": {
     "low": {
      "n": 373,
      "w": 168
     },
     "high": {
      "n": 88,
      "w": 54
     }
    },
    "offlane": {
     "low": {
      "n": 103,
      "w": 46
     },
     "high": {
      "n": 12,
      "w": 4
     }
    },
    "midlane": {
     "low": {
      "n": 28,
      "w": 13
     },
     "high": {
      "n": 17,
      "w": 10
     }
    },
    "support": {
     "low": {
      "n": 7,
      "w": 4
     },
     "high": {
      "n": 0,
      "w": 0
     }
    },
    "jungle": {
     "low": {
      "n": 17,
      "w": 8
     },
     "high": {
      "n": 5,
      "w": 3
     }
    }
   }
  },
  "feng-mao": {
   "low": {
    "n": 535,
    "w": 256
   },
   "high": {
    "n": 114,
    "w": 55
   },
   "byRole": {
    "jungle": {
     "low": {
      "n": 423,
      "w": 207
     },
     "high": {
      "n": 94,
      "w": 47
     }
    },
    "offlane": {
     "low": {
      "n": 98,
      "w": 38
     },
     "high": {
      "n": 14,
      "w": 7
     }
    },
    "midlane": {
     "low": {
      "n": 7,
      "w": 6
     },
     "high": {
      "n": 5,
      "w": 1
     }
    },
    "support": {
     "low": {
      "n": 5,
      "w": 4
     },
     "high": {
      "n": 1,
      "w": 0
     }
    },
    "carry": {
     "low": {
      "n": 2,
      "w": 1
     },
     "high": {
      "n": 0,
      "w": 0
     }
    }
   }
  },
  "gadget": {
   "low": {
    "n": 608,
    "w": 304
   },
   "high": {
    "n": 79,
    "w": 33
   },
   "byRole": {
    "midlane": {
     "low": {
      "n": 465,
      "w": 230
     },
     "high": {
      "n": 65,
      "w": 28
     }
    },
    "offlane": {
     "low": {
      "n": 36,
      "w": 18
     },
     "high": {
      "n": 3,
      "w": 0
     }
    },
    "support": {
     "low": {
      "n": 103,
      "w": 54
     },
     "high": {
      "n": 9,
      "w": 4
     }
    },
    "carry": {
     "low": {
      "n": 3,
      "w": 2
     },
     "high": {
      "n": 2,
      "w": 1
     }
    },
    "jungle": {
     "low": {
      "n": 1,
      "w": 0
     },
     "high": {
      "n": 0,
      "w": 0
     }
    }
   }
  },
  "gideon": {
   "low": {
    "n": 800,
    "w": 407
   },
   "high": {
    "n": 91,
    "w": 44
   },
   "byRole": {
    "midlane": {
     "low": {
      "n": 765,
      "w": 385
     },
     "high": {
      "n": 89,
      "w": 43
     }
    },
    "carry": {
     "low": {
      "n": 4,
      "w": 3
     },
     "high": {
      "n": 1,
      "w": 1
     }
    },
    "support": {
     "low": {
      "n": 13,
      "w": 8
     },
     "high": {
      "n": 1,
      "w": 0
     }
    },
    "offlane": {
     "low": {
      "n": 18,
      "w": 11
     },
     "high": {
      "n": 0,
      "w": 0
     }
    }
   }
  },
  "greystone": {
   "low": {
    "n": 1098,
    "w": 519
   },
   "high": {
    "n": 61,
    "w": 32
   },
   "byRole": {
    "jungle": {
     "low": {
      "n": 184,
      "w": 73
     },
     "high": {
      "n": 8,
      "w": 3
     }
    },
    "offlane": {
     "low": {
      "n": 898,
      "w": 437
     },
     "high": {
      "n": 52,
      "w": 29
     }
    },
    "midlane": {
     "low": {
      "n": 9,
      "w": 5
     },
     "high": {
      "n": 0,
      "w": 0
     }
    },
    "support": {
     "low": {
      "n": 6,
      "w": 4
     },
     "high": {
      "n": 1,
      "w": 0
     }
    },
    "carry": {
     "low": {
      "n": 1,
      "w": 0
     },
     "high": {
      "n": 0,
      "w": 0
     }
    }
   }
  },
  "grim-exe": {
   "low": {
    "n": 771,
    "w": 392
   },
   "high": {
    "n": 87,
    "w": 39
   },
   "byRole": {
    "carry": {
     "low": {
      "n": 694,
      "w": 355
     },
     "high": {
      "n": 77,
      "w": 34
     }
    },
    "midlane": {
     "low": {
      "n": 56,
      "w": 27
     },
     "high": {
      "n": 10,
      "w": 5
     }
    },
    "offlane": {
     "low": {
      "n": 17,
      "w": 9
     },
     "high": {
      "n": 0,
      "w": 0
     }
    },
    "support": {
     "low": {
      "n": 1,
      "w": 0
     },
     "high": {
      "n": 0,
      "w": 0
     }
    },
    "jungle": {
     "low": {
      "n": 3,
      "w": 1
     },
     "high": {
      "n": 0,
      "w": 0
     }
    }
   }
  },
  "grux": {
   "low": {
    "n": 1282,
    "w": 659
   },
   "high": {
    "n": 130,
    "w": 61
   },
   "byRole": {
    "offlane": {
     "low": {
      "n": 834,
      "w": 448
     },
     "high": {
      "n": 85,
      "w": 37
     }
    },
    "jungle": {
     "low": {
      "n": 411,
      "w": 191
     },
     "high": {
      "n": 40,
      "w": 22
     }
    },
    "support": {
     "low": {
      "n": 28,
      "w": 14
     },
     "high": {
      "n": 3,
      "w": 2
     }
    },
    "carry": {
     "low": {
      "n": 1,
      "w": 0
     },
     "high": {
      "n": 0,
      "w": 0
     }
    },
    "midlane": {
     "low": {
      "n": 8,
      "w": 6
     },
     "high": {
      "n": 2,
      "w": 0
     }
    }
   }
  },
  "howitzer": {
   "low": {
    "n": 434,
    "w": 231
   },
   "high": {
    "n": 61,
    "w": 27
   },
   "byRole": {
    "midlane": {
     "low": {
      "n": 371,
      "w": 193
     },
     "high": {
      "n": 54,
      "w": 25
     }
    },
    "carry": {
     "low": {
      "n": 6,
      "w": 3
     },
     "high": {
      "n": 0,
      "w": 0
     }
    },
    "support": {
     "low": {
      "n": 29,
      "w": 16
     },
     "high": {
      "n": 3,
      "w": 1
     }
    },
    "offlane": {
     "low": {
      "n": 28,
      "w": 19
     },
     "high": {
      "n": 4,
      "w": 1
     }
    }
   }
  },
  "iggy-scorch": {
   "low": {
    "n": 925,
    "w": 466
   },
   "high": {
    "n": 41,
    "w": 19
   },
   "byRole": {
    "support": {
     "low": {
      "n": 35,
      "w": 19
     },
     "high": {
      "n": 0,
      "w": 0
     }
    },
    "offlane": {
     "low": {
      "n": 287,
      "w": 158
     },
     "high": {
      "n": 15,
      "w": 5
     }
    },
    "midlane": {
     "low": {
      "n": 594,
      "w": 284
     },
     "high": {
      "n": 22,
      "w": 12
     }
    },
    "carry": {
     "low": {
      "n": 6,
      "w": 2
     },
     "high": {
      "n": 2,
      "w": 1
     }
    },
    "jungle": {
     "low": {
      "n": 3,
      "w": 3
     },
     "high": {
      "n": 2,
      "w": 1
     }
    }
   }
  },
  "ikra": {
   "low": {
    "n": 1253,
    "w": 637
   },
   "high": {
    "n": 119,
    "w": 77
   },
   "byRole": {
    "midlane": {
     "low": {
      "n": 858,
      "w": 427
     },
     "high": {
      "n": 86,
      "w": 57
     }
    },
    "support": {
     "low": {
      "n": 266,
      "w": 135
     },
     "high": {
      "n": 19,
      "w": 10
     }
    },
    "carry": {
     "low": {
      "n": 47,
      "w": 32
     },
     "high": {
      "n": 4,
      "w": 3
     }
    },
    "offlane": {
     "low": {
      "n": 78,
      "w": 41
     },
     "high": {
      "n": 10,
      "w": 7
     }
    },
    "jungle": {
     "low": {
      "n": 4,
      "w": 2
     },
     "high": {
      "n": 0,
      "w": 0
     }
    }
   }
  },
  "kallari": {
   "low": {
    "n": 461,
    "w": 237
   },
   "high": {
    "n": 103,
    "w": 62
   },
   "byRole": {
    "jungle": {
     "low": {
      "n": 439,
      "w": 228
     },
     "high": {
      "n": 103,
      "w": 62
     }
    },
    "support": {
     "low": {
      "n": 8,
      "w": 1
     },
     "high": {
      "n": 0,
      "w": 0
     }
    },
    "offlane": {
     "low": {
      "n": 5,
      "w": 4
     },
     "high": {
      "n": 0,
      "w": 0
     }
    },
    "midlane": {
     "low": {
      "n": 7,
      "w": 3
     },
     "high": {
      "n": 0,
      "w": 0
     }
    },
    "carry": {
     "low": {
      "n": 2,
      "w": 1
     },
     "high": {
      "n": 0,
      "w": 0
     }
    }
   }
  },
  "khaimera": {
   "low": {
    "n": 1673,
    "w": 852
   },
   "high": {
    "n": 110,
    "w": 46
   },
   "byRole": {
    "jungle": {
     "low": {
      "n": 1536,
      "w": 779
     },
     "high": {
      "n": 95,
      "w": 40
     }
    },
    "offlane": {
     "low": {
      "n": 122,
      "w": 66
     },
     "high": {
      "n": 15,
      "w": 6
     }
    },
    "carry": {
     "low": {
      "n": 5,
      "w": 2
     },
     "high": {
      "n": 0,
      "w": 0
     }
    },
    "midlane": {
     "low": {
      "n": 6,
      "w": 2
     },
     "high": {
      "n": 0,
      "w": 0
     }
    },
    "support": {
     "low": {
      "n": 4,
      "w": 3
     },
     "high": {
      "n": 0,
      "w": 0
     }
    }
   }
  },
  "kira": {
   "low": {
    "n": 634,
    "w": 308
   },
   "high": {
    "n": 109,
    "w": 60
   },
   "byRole": {
    "carry": {
     "low": {
      "n": 605,
      "w": 297
     },
     "high": {
      "n": 101,
      "w": 54
     }
    },
    "midlane": {
     "low": {
      "n": 15,
      "w": 6
     },
     "high": {
      "n": 5,
      "w": 4
     }
    },
    "support": {
     "low": {
      "n": 5,
      "w": 1
     },
     "high": {
      "n": 0,
      "w": 0
     }
    },
    "offlane": {
     "low": {
      "n": 9,
      "w": 4
     },
     "high": {
      "n": 3,
      "w": 2
     }
    }
   }
  },
  "kwang": {
   "low": {
    "n": 529,
    "w": 256
   },
   "high": {
    "n": 76,
    "w": 41
   },
   "byRole": {
    "jungle": {
     "low": {
      "n": 165,
      "w": 80
     },
     "high": {
      "n": 22,
      "w": 12
     }
    },
    "offlane": {
     "low": {
      "n": 327,
      "w": 157
     },
     "high": {
      "n": 47,
      "w": 28
     }
    },
    "support": {
     "low": {
      "n": 27,
      "w": 14
     },
     "high": {
      "n": 6,
      "w": 1
     }
    },
    "midlane": {
     "low": {
      "n": 10,
      "w": 5
     },
     "high": {
      "n": 0,
      "w": 0
     }
    },
    "carry": {
     "low": {
      "n": 0,
      "w": 0
     },
     "high": {
      "n": 1,
      "w": 0
     }
    }
   }
  },
  "legion": {
   "low": {
    "n": 1461,
    "w": 745
   },
   "high": {
    "n": 92,
    "w": 54
   },
   "byRole": {
    "carry": {
     "low": {
      "n": 1223,
      "w": 639
     },
     "high": {
      "n": 82,
      "w": 48
     }
    },
    "midlane": {
     "low": {
      "n": 115,
      "w": 48
     },
     "high": {
      "n": 4,
      "w": 2
     }
    },
    "support": {
     "low": {
      "n": 37,
      "w": 16
     },
     "high": {
      "n": 2,
      "w": 0
     }
    },
    "offlane": {
     "low": {
      "n": 84,
      "w": 40
     },
     "high": {
      "n": 4,
      "w": 4
     }
    },
    "jungle": {
     "low": {
      "n": 2,
      "w": 2
     },
     "high": {
      "n": 0,
      "w": 0
     }
    }
   }
  },
  "lt-belica": {
   "low": {
    "n": 799,
    "w": 384
   },
   "high": {
    "n": 67,
    "w": 40
   },
   "byRole": {
    "midlane": {
     "low": {
      "n": 418,
      "w": 199
     },
     "high": {
      "n": 45,
      "w": 28
     }
    },
    "support": {
     "low": {
      "n": 339,
      "w": 171
     },
     "high": {
      "n": 21,
      "w": 12
     }
    },
    "offlane": {
     "low": {
      "n": 15,
      "w": 2
     },
     "high": {
      "n": 0,
      "w": 0
     }
    },
    "carry": {
     "low": {
      "n": 26,
      "w": 12
     },
     "high": {
      "n": 1,
      "w": 0
     }
    },
    "jungle": {
     "low": {
      "n": 1,
      "w": 0
     },
     "high": {
      "n": 0,
      "w": 0
     }
    }
   }
  },
  "maco": {
   "low": {
    "n": 307,
    "w": 161
   },
   "high": {
    "n": 70,
    "w": 39
   },
   "byRole": {
    "support": {
     "low": {
      "n": 282,
      "w": 150
     },
     "high": {
      "n": 56,
      "w": 32
     }
    },
    "midlane": {
     "low": {
      "n": 8,
      "w": 4
     },
     "high": {
      "n": 7,
      "w": 4
     }
    },
    "offlane": {
     "low": {
      "n": 16,
      "w": 7
     },
     "high": {
      "n": 6,
      "w": 3
     }
    },
    "carry": {
     "low": {
      "n": 1,
      "w": 0
     },
     "high": {
      "n": 0,
      "w": 0
     }
    },
    "jungle": {
     "low": {
      "n": 0,
      "w": 0
     },
     "high": {
      "n": 1,
      "w": 0
     }
    }
   }
  },
  "morigesh": {
   "low": {
    "n": 401,
    "w": 175
   },
   "high": {
    "n": 34,
    "w": 20
   },
   "byRole": {
    "midlane": {
     "low": {
      "n": 315,
      "w": 139
     },
     "high": {
      "n": 23,
      "w": 13
     }
    },
    "offlane": {
     "low": {
      "n": 62,
      "w": 26
     },
     "high": {
      "n": 11,
      "w": 7
     }
    },
    "carry": {
     "low": {
      "n": 7,
      "w": 2
     },
     "high": {
      "n": 0,
      "w": 0
     }
    },
    "support": {
     "low": {
      "n": 14,
      "w": 8
     },
     "high": {
      "n": 0,
      "w": 0
     }
    },
    "jungle": {
     "low": {
      "n": 3,
      "w": 0
     },
     "high": {
      "n": 0,
      "w": 0
     }
    }
   }
  },
  "mourn": {
   "low": {
    "n": 688,
    "w": 345
   },
   "high": {
    "n": 98,
    "w": 58
   },
   "byRole": {
    "support": {
     "low": {
      "n": 590,
      "w": 301
     },
     "high": {
      "n": 79,
      "w": 47
     }
    },
    "midlane": {
     "low": {
      "n": 8,
      "w": 5
     },
     "high": {
      "n": 1,
      "w": 1
     }
    },
    "offlane": {
     "low": {
      "n": 71,
      "w": 33
     },
     "high": {
      "n": 18,
      "w": 10
     }
    },
    "jungle": {
     "low": {
      "n": 17,
      "w": 4
     },
     "high": {
      "n": 0,
      "w": 0
     }
    },
    "carry": {
     "low": {
      "n": 2,
      "w": 2
     },
     "high": {
      "n": 0,
      "w": 0
     }
    }
   }
  },
  "murdock": {
   "low": {
    "n": 1122,
    "w": 520
   },
   "high": {
    "n": 153,
    "w": 68
   },
   "byRole": {
    "carry": {
     "low": {
      "n": 915,
      "w": 418
     },
     "high": {
      "n": 139,
      "w": 63
     }
    },
    "midlane": {
     "low": {
      "n": 29,
      "w": 15
     },
     "high": {
      "n": 5,
      "w": 1
     }
    },
    "offlane": {
     "low": {
      "n": 164,
      "w": 79
     },
     "high": {
      "n": 9,
      "w": 4
     }
    },
    "support": {
     "low": {
      "n": 13,
      "w": 7
     },
     "high": {
      "n": 0,
      "w": 0
     }
    },
    "jungle": {
     "low": {
      "n": 1,
      "w": 1
     },
     "high": {
      "n": 0,
      "w": 0
     }
    }
   }
  },
  "muriel": {
   "low": {
    "n": 298,
    "w": 155
   },
   "high": {
    "n": 71,
    "w": 41
   },
   "byRole": {
    "support": {
     "low": {
      "n": 289,
      "w": 153
     },
     "high": {
      "n": 68,
      "w": 41
     }
    },
    "offlane": {
     "low": {
      "n": 5,
      "w": 1
     },
     "high": {
      "n": 2,
      "w": 0
     }
    },
    "jungle": {
     "low": {
      "n": 1,
      "w": 0
     },
     "high": {
      "n": 0,
      "w": 0
     }
    },
    "midlane": {
     "low": {
      "n": 3,
      "w": 1
     },
     "high": {
      "n": 0,
      "w": 0
     }
    },
    "carry": {
     "low": {
      "n": 0,
      "w": 0
     },
     "high": {
      "n": 1,
      "w": 0
     }
    }
   }
  },
  "narbash": {
   "low": {
    "n": 430,
    "w": 221
   },
   "high": {
    "n": 49,
    "w": 23
   },
   "byRole": {
    "support": {
     "low": {
      "n": 418,
      "w": 215
     },
     "high": {
      "n": 48,
      "w": 23
     }
    },
    "carry": {
     "low": {
      "n": 0,
      "w": 0
     },
     "high": {
      "n": 1,
      "w": 0
     }
    },
    "jungle": {
     "low": {
      "n": 8,
      "w": 4
     },
     "high": {
      "n": 0,
      "w": 0
     }
    },
    "offlane": {
     "low": {
      "n": 4,
      "w": 2
     },
     "high": {
      "n": 0,
      "w": 0
     }
    }
   }
  },
  "neon": {
   "low": {
    "n": 475,
    "w": 204
   },
   "high": {
    "n": 90,
    "w": 40
   },
   "byRole": {
    "midlane": {
     "low": {
      "n": 455,
      "w": 194
     },
     "high": {
      "n": 89,
      "w": 39
     }
    },
    "support": {
     "low": {
      "n": 9,
      "w": 6
     },
     "high": {
      "n": 0,
      "w": 0
     }
    },
    "carry": {
     "low": {
      "n": 4,
      "w": 1
     },
     "high": {
      "n": 0,
      "w": 0
     }
    },
    "offlane": {
     "low": {
      "n": 6,
      "w": 3
     },
     "high": {
      "n": 1,
      "w": 1
     }
    },
    "jungle": {
     "low": {
      "n": 1,
      "w": 0
     },
     "high": {
      "n": 0,
      "w": 0
     }
    }
   }
  },
  "phase": {
   "low": {
    "n": 1095,
    "w": 546
   },
   "high": {
    "n": 110,
    "w": 63
   },
   "byRole": {
    "support": {
     "low": {
      "n": 1073,
      "w": 540
     },
     "high": {
      "n": 108,
      "w": 61
     }
    },
    "carry": {
     "low": {
      "n": 11,
      "w": 5
     },
     "high": {
      "n": 1,
      "w": 1
     }
    },
    "offlane": {
     "low": {
      "n": 4,
      "w": 0
     },
     "high": {
      "n": 0,
      "w": 0
     }
    },
    "midlane": {
     "low": {
      "n": 6,
      "w": 1
     },
     "high": {
      "n": 1,
      "w": 1
     }
    },
    "jungle": {
     "low": {
      "n": 1,
      "w": 0
     },
     "high": {
      "n": 0,
      "w": 0
     }
    }
   }
  },
  "rampage": {
   "low": {
    "n": 573,
    "w": 311
   },
   "high": {
    "n": 118,
    "w": 69
   },
   "byRole": {
    "jungle": {
     "low": {
      "n": 509,
      "w": 279
     },
     "high": {
      "n": 101,
      "w": 59
     }
    },
    "support": {
     "low": {
      "n": 14,
      "w": 5
     },
     "high": {
      "n": 12,
      "w": 7
     }
    },
    "offlane": {
     "low": {
      "n": 46,
      "w": 26
     },
     "high": {
      "n": 5,
      "w": 3
     }
    },
    "midlane": {
     "low": {
      "n": 4,
      "w": 1
     },
     "high": {
      "n": 0,
      "w": 0
     }
    }
   }
  },
  "renna": {
   "low": {
    "n": 1028,
    "w": 542
   },
   "high": {
    "n": 72,
    "w": 40
   },
   "byRole": {
    "midlane": {
     "low": {
      "n": 961,
      "w": 508
     },
     "high": {
      "n": 68,
      "w": 38
     }
    },
    "support": {
     "low": {
      "n": 50,
      "w": 25
     },
     "high": {
      "n": 4,
      "w": 2
     }
    },
    "offlane": {
     "low": {
      "n": 14,
      "w": 7
     },
     "high": {
      "n": 0,
      "w": 0
     }
    },
    "carry": {
     "low": {
      "n": 3,
      "w": 2
     },
     "high": {
      "n": 0,
      "w": 0
     }
    }
   }
  },
  "revenant": {
   "low": {
    "n": 734,
    "w": 359
   },
   "high": {
    "n": 136,
    "w": 69
   },
   "byRole": {
    "carry": {
     "low": {
      "n": 642,
      "w": 314
     },
     "high": {
      "n": 128,
      "w": 64
     }
    },
    "midlane": {
     "low": {
      "n": 51,
      "w": 27
     },
     "high": {
      "n": 7,
      "w": 5
     }
    },
    "support": {
     "low": {
      "n": 9,
      "w": 3
     },
     "high": {
      "n": 0,
      "w": 0
     }
    },
    "offlane": {
     "low": {
      "n": 32,
      "w": 15
     },
     "high": {
      "n": 1,
      "w": 0
     }
    }
   }
  },
  "riktor": {
   "low": {
    "n": 980,
    "w": 496
   },
   "high": {
    "n": 147,
    "w": 62
   },
   "byRole": {
    "support": {
     "low": {
      "n": 790,
      "w": 396
     },
     "high": {
      "n": 101,
      "w": 43
     }
    },
    "jungle": {
     "low": {
      "n": 93,
      "w": 49
     },
     "high": {
      "n": 13,
      "w": 4
     }
    },
    "offlane": {
     "low": {
      "n": 94,
      "w": 50
     },
     "high": {
      "n": 30,
      "w": 13
     }
    },
    "carry": {
     "low": {
      "n": 1,
      "w": 0
     },
     "high": {
      "n": 3,
      "w": 2
     }
    },
    "midlane": {
     "low": {
      "n": 2,
      "w": 1
     },
     "high": {
      "n": 0,
      "w": 0
     }
    }
   }
  },
  "serath": {
   "low": {
    "n": 978,
    "w": 482
   },
   "high": {
    "n": 71,
    "w": 39
   },
   "byRole": {
    "offlane": {
     "low": {
      "n": 96,
      "w": 38
     },
     "high": {
      "n": 4,
      "w": 3
     }
    },
    "jungle": {
     "low": {
      "n": 879,
      "w": 442
     },
     "high": {
      "n": 67,
      "w": 36
     }
    },
    "midlane": {
     "low": {
      "n": 2,
      "w": 1
     },
     "high": {
      "n": 0,
      "w": 0
     }
    },
    "support": {
     "low": {
      "n": 1,
      "w": 1
     },
     "high": {
      "n": 0,
      "w": 0
     }
    }
   }
  },
  "sevarog": {
   "low": {
    "n": 336,
    "w": 156
   },
   "high": {
    "n": 38,
    "w": 24
   },
   "byRole": {
    "offlane": {
     "low": {
      "n": 245,
      "w": 114
     },
     "high": {
      "n": 30,
      "w": 19
     }
    },
    "jungle": {
     "low": {
      "n": 85,
      "w": 41
     },
     "high": {
      "n": 6,
      "w": 3
     }
    },
    "carry": {
     "low": {
      "n": 1,
      "w": 1
     },
     "high": {
      "n": 0,
      "w": 0
     }
    },
    "midlane": {
     "low": {
      "n": 2,
      "w": 0
     },
     "high": {
      "n": 2,
      "w": 2
     }
    },
    "support": {
     "low": {
      "n": 3,
      "w": 0
     },
     "high": {
      "n": 0,
      "w": 0
     }
    }
   }
  },
  "shinbi": {
   "low": {
    "n": 668,
    "w": 331
   },
   "high": {
    "n": 143,
    "w": 67
   },
   "byRole": {
    "offlane": {
     "low": {
      "n": 578,
      "w": 290
     },
     "high": {
      "n": 120,
      "w": 59
     }
    },
    "jungle": {
     "low": {
      "n": 67,
      "w": 28
     },
     "high": {
      "n": 10,
      "w": 4
     }
    },
    "midlane": {
     "low": {
      "n": 21,
      "w": 12
     },
     "high": {
      "n": 13,
      "w": 4
     }
    },
    "carry": {
     "low": {
      "n": 1,
      "w": 0
     },
     "high": {
      "n": 0,
      "w": 0
     }
    },
    "support": {
     "low": {
      "n": 1,
      "w": 1
     },
     "high": {
      "n": 0,
      "w": 0
     }
    }
   }
  },
  "skylar": {
   "low": {
    "n": 724,
    "w": 382
   },
   "high": {
    "n": 87,
    "w": 46
   },
   "byRole": {
    "carry": {
     "low": {
      "n": 603,
      "w": 311
     },
     "high": {
      "n": 74,
      "w": 38
     }
    },
    "midlane": {
     "low": {
      "n": 67,
      "w": 38
     },
     "high": {
      "n": 12,
      "w": 7
     }
    },
    "offlane": {
     "low": {
      "n": 45,
      "w": 30
     },
     "high": {
      "n": 1,
      "w": 1
     }
    },
    "support": {
     "low": {
      "n": 9,
      "w": 3
     },
     "high": {
      "n": 0,
      "w": 0
     }
    }
   }
  },
  "sparrow": {
   "low": {
    "n": 1677,
    "w": 877
   },
   "high": {
    "n": 162,
    "w": 79
   },
   "byRole": {
    "carry": {
     "low": {
      "n": 1593,
      "w": 838
     },
     "high": {
      "n": 159,
      "w": 78
     }
    },
    "offlane": {
     "low": {
      "n": 38,
      "w": 15
     },
     "high": {
      "n": 2,
      "w": 1
     }
    },
    "midlane": {
     "low": {
      "n": 37,
      "w": 20
     },
     "high": {
      "n": 1,
      "w": 0
     }
    },
    "support": {
     "low": {
      "n": 8,
      "w": 3
     },
     "high": {
      "n": 0,
      "w": 0
     }
    },
    "jungle": {
     "low": {
      "n": 1,
      "w": 1
     },
     "high": {
      "n": 0,
      "w": 0
     }
    }
   }
  },
  "steel": {
   "low": {
    "n": 1590,
    "w": 832
   },
   "high": {
    "n": 152,
    "w": 75
   },
   "byRole": {
    "offlane": {
     "low": {
      "n": 410,
      "w": 209
     },
     "high": {
      "n": 49,
      "w": 25
     }
    },
    "support": {
     "low": {
      "n": 1111,
      "w": 587
     },
     "high": {
      "n": 101,
      "w": 50
     }
    },
    "jungle": {
     "low": {
      "n": 64,
      "w": 35
     },
     "high": {
      "n": 2,
      "w": 0
     }
    },
    "carry": {
     "low": {
      "n": 4,
      "w": 0
     },
     "high": {
      "n": 0,
      "w": 0
     }
    },
    "midlane": {
     "low": {
      "n": 1,
      "w": 1
     },
     "high": {
      "n": 0,
      "w": 0
     }
    }
   }
  },
  "terra": {
   "low": {
    "n": 461,
    "w": 218
   },
   "high": {
    "n": 58,
    "w": 28
   },
   "byRole": {
    "offlane": {
     "low": {
      "n": 363,
      "w": 174
     },
     "high": {
      "n": 52,
      "w": 26
     }
    },
    "support": {
     "low": {
      "n": 17,
      "w": 7
     },
     "high": {
      "n": 3,
      "w": 1
     }
    },
    "jungle": {
     "low": {
      "n": 73,
      "w": 33
     },
     "high": {
      "n": 3,
      "w": 1
     }
    },
    "midlane": {
     "low": {
      "n": 8,
      "w": 4
     },
     "high": {
      "n": 0,
      "w": 0
     }
    }
   }
  },
  "the-fey": {
   "low": {
    "n": 1204,
    "w": 604
   },
   "high": {
    "n": 154,
    "w": 84
   },
   "byRole": {
    "midlane": {
     "low": {
      "n": 1030,
      "w": 524
     },
     "high": {
      "n": 135,
      "w": 77
     }
    },
    "support": {
     "low": {
      "n": 143,
      "w": 64
     },
     "high": {
      "n": 16,
      "w": 6
     }
    },
    "carry": {
     "low": {
      "n": 12,
      "w": 7
     },
     "high": {
      "n": 1,
      "w": 0
     }
    },
    "offlane": {
     "low": {
      "n": 19,
      "w": 9
     },
     "high": {
      "n": 2,
      "w": 1
     }
    }
   }
  },
  "twinblast": {
   "low": {
    "n": 601,
    "w": 296
   },
   "high": {
    "n": 75,
    "w": 41
   },
   "byRole": {
    "carry": {
     "low": {
      "n": 533,
      "w": 261
     },
     "high": {
      "n": 66,
      "w": 36
     }
    },
    "offlane": {
     "low": {
      "n": 39,
      "w": 19
     },
     "high": {
      "n": 1,
      "w": 1
     }
    },
    "midlane": {
     "low": {
      "n": 22,
      "w": 13
     },
     "high": {
      "n": 8,
      "w": 4
     }
    },
    "support": {
     "low": {
      "n": 7,
      "w": 3
     },
     "high": {
      "n": 0,
      "w": 0
     }
    }
   }
  },
  "wraith": {
   "low": {
    "n": 561,
    "w": 264
   },
   "high": {
    "n": 85,
    "w": 35
   },
   "byRole": {
    "carry": {
     "low": {
      "n": 171,
      "w": 80
     },
     "high": {
      "n": 14,
      "w": 5
     }
    },
    "midlane": {
     "low": {
      "n": 319,
      "w": 147
     },
     "high": {
      "n": 52,
      "w": 23
     }
    },
    "support": {
     "low": {
      "n": 65,
      "w": 34
     },
     "high": {
      "n": 17,
      "w": 7
     }
    },
    "offlane": {
     "low": {
      "n": 6,
      "w": 3
     },
     "high": {
      "n": 2,
      "w": 0
     }
    }
   }
  },
  "wukong": {
   "low": {
    "n": 221,
    "w": 98
   },
   "high": {
    "n": 47,
    "w": 22
   },
   "byRole": {
    "offlane": {
     "low": {
      "n": 59,
      "w": 32
     },
     "high": {
      "n": 14,
      "w": 11
     }
    },
    "jungle": {
     "low": {
      "n": 141,
      "w": 58
     },
     "high": {
      "n": 31,
      "w": 11
     }
    },
    "support": {
     "low": {
      "n": 13,
      "w": 7
     },
     "high": {
      "n": 1,
      "w": 0
     }
    },
    "midlane": {
     "low": {
      "n": 8,
      "w": 1
     },
     "high": {
      "n": 1,
      "w": 0
     }
    }
   }
  },
  "yin": {
   "low": {
    "n": 531,
    "w": 264
   },
   "high": {
    "n": 41,
    "w": 23
   },
   "byRole": {
    "jungle": {
     "low": {
      "n": 385,
      "w": 192
     },
     "high": {
      "n": 32,
      "w": 16
     }
    },
    "offlane": {
     "low": {
      "n": 116,
      "w": 58
     },
     "high": {
      "n": 6,
      "w": 5
     }
    },
    "midlane": {
     "low": {
      "n": 11,
      "w": 6
     },
     "high": {
      "n": 3,
      "w": 2
     }
    },
    "support": {
     "low": {
      "n": 3,
      "w": 1
     },
     "high": {
      "n": 0,
      "w": 0
     }
    },
    "carry": {
     "low": {
      "n": 16,
      "w": 7
     },
     "high": {
      "n": 0,
      "w": 0
     }
    }
   }
  },
  "yurei": {
   "low": {
    "n": 356,
    "w": 153
   },
   "high": {
    "n": 75,
    "w": 38
   },
   "byRole": {
    "jungle": {
     "low": {
      "n": 298,
      "w": 132
     },
     "high": {
      "n": 60,
      "w": 34
     }
    },
    "support": {
     "low": {
      "n": 3,
      "w": 2
     },
     "high": {
      "n": 0,
      "w": 0
     }
    },
    "offlane": {
     "low": {
      "n": 51,
      "w": 17
     },
     "high": {
      "n": 12,
      "w": 4
     }
    },
    "midlane": {
     "low": {
      "n": 4,
      "w": 2
     },
     "high": {
      "n": 1,
      "w": 0
     }
    },
    "carry": {
     "low": {
      "n": 0,
      "w": 0
     },
     "high": {
      "n": 2,
      "w": 0
     }
    }
   }
  },
  "zarus": {
   "low": {
    "n": 846,
    "w": 416
   },
   "high": {
    "n": 176,
    "w": 94
   },
   "byRole": {
    "jungle": {
     "low": {
      "n": 511,
      "w": 258
     },
     "high": {
      "n": 115,
      "w": 63
     }
    },
    "offlane": {
     "low": {
      "n": 328,
      "w": 155
     },
     "high": {
      "n": 54,
      "w": 30
     }
    },
    "support": {
     "low": {
      "n": 7,
      "w": 3
     },
     "high": {
      "n": 7,
      "w": 1
     }
    }
   }
  },
  "zinx": {
   "low": {
    "n": 965,
    "w": 477
   },
   "high": {
    "n": 59,
    "w": 23
   },
   "byRole": {
    "support": {
     "low": {
      "n": 658,
      "w": 304
     },
     "high": {
      "n": 31,
      "w": 9
     }
    },
    "midlane": {
     "low": {
      "n": 80,
      "w": 45
     },
     "high": {
      "n": 12,
      "w": 4
     }
    },
    "offlane": {
     "low": {
      "n": 167,
      "w": 99
     },
     "high": {
      "n": 12,
      "w": 8
     }
    },
    "carry": {
     "low": {
      "n": 57,
      "w": 27
     },
     "high": {
      "n": 3,
      "w": 1
     }
    },
    "jungle": {
     "low": {
      "n": 3,
      "w": 2
     },
     "high": {
      "n": 1,
      "w": 1
     }
    }
   }
  }
 }
}