{
 "rounds": [
  {
   "round": 1,
   "at": "2026-06-22T05:35:36.487Z",
   "agreementRate": 0.75,
   "flaggedLines": 3,
   "auditScore": 1,
   "hardFail": false,
   "applied": 18
  },
  {
   "round": 2,
   "at": "2026-06-22T05:39:29.197Z",
   "agreementRate": 0.917,
   "flaggedLines": 1,
   "auditScore": 1,
   "hardFail": false,
   "applied": 3
  },
  {
   "round": 3,
   "at": "2026-06-22T05:42:06.001Z",
   "agreementRate": 1,
   "flaggedLines": 0,
   "auditScore": 1,
   "hardFail": false,
   "applied": 3
  },
  {
   "round": 4,
   "at": "2026-06-22T14:12:34.802Z",
   "agreementRate": 0.833,
   "flaggedLines": 2,
   "auditScore": 1,
   "hardFail": false,
   "applied": 5
  },
  {
   "round": 5,
   "at": "2026-06-22T14:12:35.598Z",
   "agreementRate": 1,
   "flaggedLines": 0,
   "auditScore": 1,
   "hardFail": false,
   "applied": 1
  }
 ]
}