{
  "Void Conduit": "img/items/void-conduit.webp",
  "Spirit Locket": "img/items/spirit-locket.webp",
  "Onixian Quiver": "img/items/onixian-quiver.webp",
  "Sanctification": "img/items/sanctification.webp",
  "Azure Core": "img/items/azure-core.webp",
  "Saphir's Mantle": "img/items/saphirs-mantle.webp",
  "Galaxy Greaves": "img/items/galaxy-greaves.webp",
  "Witchstalker": "img/items/witchstalker.webp",
  "Augmentation": "img/items/augmentation.webp",
  "Time-Flux Band": "img/items/time-flux-band.webp",
  "Crescelia": "img/items/crescelia.webp",
  "Catalytic Drive": "img/items/catalytic-drive.webp",
  "Goliath Crest": "img/items/goliath-crest.webp",
  "Energy Stream": "img/items/energy-stream.webp",
  "Orion": "img/items/orion.webp",
  "Absolution": "img/items/absolution.webp",
  "Tenacious Drape": "img/items/tenacious-drape.webp",
  "Winter's Fury": "img/items/winters-fury.webp",
  "Honed Kris": "img/items/honed-kris.webp",
  "Giant's Ring": "img/items/giants-ring.webp",
  "Razorback": "img/items/razorback.webp",
  "Spirit Beads": "img/items/spirit-beads.webp",
  "Loch Shawl": "img/items/loch-shawl.webp",
  "Raiment of Renewal": "img/items/raiment-of-renewal.webp",
  "Storm Breaker": "img/items/storm-breaker.webp",
  "Imperator": "img/items/imperator.webp",
  "Tainted Blade": "img/items/tainted-blade.webp",
  "Solstone Drone": "img/items/solstone-drone.webp",
  "Ashbringer": "img/items/ashbringer.webp",
  "Liberator": "img/items/liberator.webp",
  "Wizard Crest": "img/items/wizard-crest.webp",
  "Painweaver": "img/items/painweaver.webp",
  "Noxia": "img/items/noxia.webp",
  "Cursed Scroll": "img/items/cursed-scroll.webp",
  "Stealth Ward": "img/items/stealth-ward.webp",
  "Rebirth": "img/items/rebirth.webp",
  "Mesmer": "img/items/mesmer.webp",
  "Plasma Blade": "img/items/plasma-blade.webp",
  "Penumbra": "img/items/penumbra.webp",
  "Pendant": "img/items/pendant.webp",
  "Champion Crest": "img/items/champion-crest.webp",
  "Fire Blossom": "img/items/fire-blossom.webp",
  "Marksman Crest": "img/items/marksman-crest.webp",
  "Titan Crest": "img/items/titan-crest.webp",
  "Dust Devil": "img/items/dust-devil.webp",
  "Silentium": "img/items/silentium.webp",
  "Gravitum": "img/items/gravitum.webp",
  "Brimstone": "img/items/brimstone.webp",
  "Pygmy Dust": "img/items/pygmy-dust.webp",
  "Serrated Blade": "img/items/serrated-blade.webp",
  "Spell Slasher": "img/items/spell-slasher.webp",
  "Draconum": "img/items/draconum.webp",
  "Eviscerator": "img/items/eviscerator.webp",
  "Zealous Tomahawk": "img/items/zealous-tomahawk.webp",
  "Berserker's Axe": "img/items/berserkers-axe.webp",
  "Occult Crest": "img/items/occult-crest.webp",
  "Scepter": "img/items/scepter.webp",
  "Heroic Guard": "img/items/heroic-guard.webp",
  "Scattershot": "img/items/scattershot.webp",
  "Ironwood Warbow": "img/items/ironwood-warbow.webp",
  "Wild Hunt": "img/items/wild-hunt.webp",
  "Necrosis": "img/items/necrosis.webp",
  "Sai": "img/items/sai.webp",
  "Unbroken Will": "img/items/unbroken-will.webp",
  "Tainted Rounds": "img/items/tainted-rounds.webp",
  "Pacifier": "img/items/pacifier.webp",
  "Cursed Ring": "img/items/cursed-ring.webp",
  "Devotion": "img/items/devotion.webp",
  "Razorclaw": "img/items/razorclaw.webp",
  "Warden Crest": "img/items/warden-crest.webp",
  "Scalding Sceptre": "img/items/scalding-sceptre.webp",
  "Aegis Of Agawar": "img/items/aegis-of-agawar.webp",
  "Nyr Warboots": "img/items/nyr-warboots.webp",
  "Earth Spirit": "img/items/earth-spirit.webp",
  "Solstice": "img/items/solstice.webp",
  "Keeper Crest": "img/items/keeper-crest.webp",
  "Stalwart Gauntlets": "img/items/stalwart-gauntlets.webp",
  "Epoch": "img/items/epoch.webp",
  "Consort Crest": "img/items/consort-crest.webp",
  "Dusk Stave": "img/items/dusk-stave.webp",
  "Soul Chalice": "img/items/soul-chalice.webp",
  "Steel Mail": "img/items/steel-mail.webp",
  "The Perforator": "img/items/the-perforator.webp",
  "Echelon Cloak": "img/items/echelon-cloak.webp",
  "Leather Tunic": "img/items/leather-tunic.webp",
  "Spectral Schematics": "img/items/spectral-schematics.webp",
  "Codex": "img/items/codex.webp",
  "Citadel": "img/items/citadel.webp",
  "Divine Pouch": "img/items/divine-pouch.webp",
  "Claw Of Hermes": "img/items/claw-of-hermes.webp",
  "Essence Ring": "img/items/essence-ring.webp",
  "Claymore": "img/items/claymore.webp",
  "Temporal Ripper": "img/items/temporal-ripper.webp",
  "Lightning Hawk": "img/items/lightning-hawk.webp",
  "Tranquility": "img/items/tranquility.webp",
  "Ortus": "img/items/ortus.webp",
  "Wraith Leggings": "img/items/wraith-leggings.webp",
  "Abyssal Dart": "img/items/abyssal-dart.webp",
  "Cybernetic Drive": "img/items/cybernetic-drive.webp",
  "Inquisition": "img/items/inquisition.webp",
  "Ruination": "img/items/ruination.webp",
  "Strength Tonic": "img/items/strength-tonic.webp",
  "Cerulean Stone": "img/items/cerulean-stone.webp",
  "Diffusal Cane": "img/items/diffusal-cane.webp",
  "Spirit Shiv": "img/items/spirit-shiv.webp",
  "Omen": "img/items/omen.webp",
  "Typhoon": "img/items/typhoon.webp",
  "Crimson Edge": "img/items/crimson-edge.webp",
  "Leafsong": "img/items/leafsong.webp",
  "Spellbreaker": "img/items/spellbreaker.webp",
  "Magnify": "img/items/magnify.webp",
  "Frostguard": "img/items/frostguard.webp",
  "Exodus": "img/items/exodus.webp",
  "Magician Crest": "img/items/magician-crest.webp",
  "Warden's Faith": "img/items/wardens-faith.webp",
  "Stamina Tonic": "img/items/stamina-tonic.webp",
  "Life Stream": "img/items/life-stream.webp",
  "Shortsword": "img/items/shortsword.webp",
  "Obelisk": "img/items/obelisk.webp",
  "Potent Staff": "img/items/potent-staff.webp",
  "Legacy": "img/items/legacy.webp",
  "Nether Shard": "img/items/nether-shard.webp",
  "Lifecore": "img/items/lifecore.webp",
  "Iceskorn Talons": "img/items/iceskorn-talons.webp",
  "Greatsword": "img/items/greatsword.webp",
  "Tainted Charm": "img/items/tainted-charm.webp",
  "Divine Potion": "img/items/divine-potion.webp",
  "Robust Arbalest": "img/items/robust-arbalest.webp",
  "Gaia Greaves": "img/items/gaia-greaves.webp",
  "Dynamo": "img/items/dynamo.webp",
  "Alchemical Rod": "img/items/alchemical-rod.webp",
  "Salvation": "img/items/salvation.webp",
  "Vanguardian": "img/items/vanguardian.webp",
  "Lucky Feather": "img/items/lucky-feather.webp",
  "Nex": "img/items/nex.webp",
  "Fortified Mantle": "img/items/fortified-mantle.webp",
  "Mindrazor": "img/items/mindrazor.webp",
  "Protection Tonic": "img/items/protection-tonic.webp",
  "Lunaria": "img/items/lunaria.webp",
  "Spectra": "img/items/spectra.webp",
  "Blood Tome": "img/items/blood-tome.webp",
  "Sentry": "img/items/sentry.webp",
  "Runic Veil": "img/items/runic-veil.webp",
  "Chaotic Core": "img/items/chaotic-core.webp",
  "Reclamation": "img/items/reclamation.webp",
  "Refillable Potion": "img/items/refillable-potion.webp",
  "Megacosm": "img/items/megacosm.webp",
  "Brutallax": "img/items/brutallax.webp",
  "Warp Stream": "img/items/warp-stream.webp",
  "Tainted Scepter": "img/items/tainted-scepter.webp",
  "Ruthless Broadsword": "img/items/ruthless-broadsword.webp",
  "Mistmeadow Buckler": "img/items/mistmeadow-buckler.webp",
  "Rift Walkers": "img/items/rift-walkers.webp",
  "Syonic Echo": "img/items/syonic-echo.webp",
  "Barbaric Cleaver": "img/items/barbaric-cleaver.webp",
  "Alternata": "img/items/alternata.webp",
  "Elafrost": "img/items/elafrost.webp",
  "Tainted Trident": "img/items/tainted-trident.webp",
  "Enra's Blessing": "img/items/enras-blessing.webp",
  "Crystal Tear": "img/items/crystal-tear.webp",
  "Fist Of Razuul": "img/items/fist-of-razuul.webp",
  "Xenia": "img/items/xenia.webp",
  "Sharpshooter Crest": "img/items/sharpshooter-crest.webp",
  "Horned Plate": "img/items/horned-plate.webp",
  "Orb Of Enlightenment": "img/items/orb-of-enlightenment.webp",
  "Nullifying Mask": "img/items/nullifying-mask.webp",
  "Mutilator": "img/items/mutilator.webp",
  "Tainted Bastion": "img/items/tainted-bastion.webp",
  "Vigorous Amulet": "img/items/vigorous-amulet.webp",
  "Solstone": "img/items/solstone.webp",
  "Assassin Crest": "img/items/assassin-crest.webp",
  "Crossbow": "img/items/crossbow.webp",
  "Basilisk": "img/items/basilisk.webp",
  "Crystalline Cuirass": "img/items/crystalline-cuirass.webp",
  "Tyranny": "img/items/tyranny.webp",
  "Imbued Amulet": "img/items/imbued-amulet.webp",
  "Volcanica": "img/items/volcanica.webp",
  "Violet Brooch": "img/items/violet-brooch.webp",
  "Marshal": "img/items/marshal.webp",
  "Stonewall": "img/items/stonewall.webp",
  "Dawnstar": "img/items/dawnstar.webp",
  "Alternator": "img/items/alternator.webp",
  "Hexbound Bracers": "img/items/hexbound-bracers.webp",
  "Nightfall": "img/items/nightfall.webp",
  "Prophecy": "img/items/prophecy.webp",
  "Overseer": "img/items/overseer.webp",
  "Resolution": "img/items/resolution.webp",
  "Truesilver Bracelet": "img/items/truesilver-bracelet.webp",
  "Rune Bow": "img/items/rune-bow.webp",
  "Timewarp": "img/items/timewarp.webp",
  "Divine Wreath": "img/items/divine-wreath.webp",
  "Void Crystal": "img/items/void-crystal.webp",
  "Envy": "img/items/envy.webp",
  "Judgement": "img/items/judgement.webp",
  "Bloodletter": "img/items/bloodletter.webp",
  "Solaris": "img/items/solaris.webp",
  "Spear Of Desolation": "img/items/spear-of-desolation.webp",
  "Rapid Rapier": "img/items/rapid-rapier.webp",
  "Hunt": "img/items/hunt.webp",
  "Intellect Tonic": "img/items/intellect-tonic.webp",
  "Flux Matrix": "img/items/flux-matrix.webp",
  "Transference": "img/items/transference.webp",
  "Overlord": "img/items/overlord.webp",
  "Composite Bow": "img/items/composite-bow.webp",
  "Deathstalker": "img/items/deathstalker.webp",
  "Void Helm": "img/items/void-helm.webp",
  "Lifebinder": "img/items/lifebinder.webp",
  "Amulet Of Chaos": "img/items/amulet-of-chaos.webp",
  "Manta Scythe": "img/items/manta-scythe.webp",
  "World Breaker": "img/items/world-breaker.webp",
  "Rejuvenation Robe": "img/items/rejuvenation-robe.webp",
  "Gilded Pendant": "img/items/gilded-pendant.webp",
  "Orb Of Growth": "img/items/orb-of-growth.webp",
  "Soulbinder": "img/items/soulbinder.webp",
  "Tempest": "img/items/tempest.webp",
  "Everbloom": "img/items/everbloom.webp",
  "Sonar Drone": "img/items/sonar-drone.webp",
  "Dreambinder": "img/items/dreambinder.webp",
  "Infernum": "img/items/infernum.webp",
  "Astral Catalyst": "img/items/astral-catalyst.webp",
  "Stone Of Strength": "img/items/stone-of-strength.webp",
  "Rogue Crest": "img/items/rogue-crest.webp",
  "Gaussian Greaves": "img/items/gaussian-greaves.webp",
  "Combustion": "img/items/combustion.webp",
  "Life Ring": "img/items/life-ring.webp",
  "Tenacious Gem": "img/items/tenacious-gem.webp",
  "Warlock Crest": "img/items/warlock-crest.webp",
  "Malady": "img/items/malady.webp",
  "Warrior Crest": "img/items/warrior-crest.webp",
  "Banded Emerald": "img/items/banded-emerald.webp",
  "Caustica": "img/items/caustica.webp",
  "Demon Edge": "img/items/demon-edge.webp",
  "Demolisher": "img/items/demolisher.webp",
  "Wraps": "img/items/wraps.webp",
  "Spiked Birch": "img/items/spiked-birch.webp",
  "Tainted Totem": "img/items/tainted-totem.webp",
  "Tainted Guard": "img/items/tainted-guard.webp",
  "Oblivion Crown": "img/items/oblivion-crown.webp",
  "Mystic Cane": "img/items/mystic-cane.webp",
  "Longbow": "img/items/longbow.webp",
  "Sky Splitter": "img/items/sky-splitter.webp",
  "Golem's Gift": "img/items/golems-gift.webp",
  "Voidgazer": "img/items/voidgazer.webp",
  "Soulbearer": "img/items/soulbearer.webp",
  "Spirit Of Amir": "img/items/spirit-of-amir.webp",
  "Redwood Shortbow": "img/items/redwood-shortbow.webp",
  "Windcaller": "img/items/windcaller.webp",
  "Equinox": "img/items/equinox.webp",
  "Vitality Beads": "img/items/vitality-beads.webp",
  "Earthshaker": "img/items/earthshaker.webp",
  "Nuclear Rounds": "img/items/nuclear-rounds.webp",
  "Entropy": "img/items/entropy.webp",
  "Rapture": "img/items/rapture.webp",
  "Florescence": "img/items/florescence.webp",
  "Vyzar Carapace": "img/items/vyzar-carapace.webp",
  "Terminus": "img/items/terminus.webp",
  "Dread": "img/items/dread.webp",
  "Guardian Crest": "img/items/guardian-crest.webp",
  "Oathkeeper": "img/items/oathkeeper.webp",
  "Polar Treads": "img/items/polar-treads.webp",
  "Barbed Pauldron": "img/items/barbed-pauldron.webp",
  "Vainglory": "img/items/vainglory.webp",
  "Luxforge Lantern": "img/items/luxforge-lantern.webp",
  "Sabre": "img/items/sabre.webp",
  "Frosted Lure": "img/items/frosted-lure.webp",
  "Tunic": "img/items/tunic.webp",
  "Chronomatic Wand": "img/items/chronomatic-wand.webp",
  "Viper": "img/items/viper.webp",
  "Vanquisher": "img/items/vanquisher.webp"
}